Workbook

Sheet Row data
A1: SL | B1: CompName | C1: EmpId | D1: Employee Name | E1: DeptName | F1: SectName | G1: DesigName | H1: AccountNo | I1: JDate | J1: QuitDate | K1: Quit_Year | L1: BirthDate | M1: Age | N1: Gender | O1: OT | P1: Employee Category | Q1: Gross | R1: Gross Pay | S1: Basic | T1: HRent | U1: Medical | V1: TechAllowance | W1: ExtraTechAllow | X1: OthersAllowance | Y1: FoodAllowance | Z1: ConvAllowance | AA1: Attendance Bonus | AB1: OT Amount | AC1: Adjustment Deduction | AD1: Adjustment Addition | AE1: Absent Amount | AF1: Late Amount | AG1: Loan | AH1: Tax | AI1: Stamp | AJ1: Net Payable | AK1: Bank | AL1: Cash
A2: 1 | B2: ABC Company Ltd. | C2: 8143412 | D2: Abdullah | E2: Production | F2: Allora | G2: Trainee Officer | H2: 9993204000003460 | I2: 45078 | L2: 37622 | M2: =IF('Row data'!$J2="",DATEDIF('Row data'!$L2,TODAY(),"y"),"0") -> 23 | N2: M | O2: N | P2: Staff | Q2: 16305 | R2: 16305 | S2: 9783 | T2: 4892 | U2: 652 | V2: 489 | W2: 0 | X2: 0 | Y2: 489 | Z2: 489 | AA2: 0 | AB2: 0 | AC2: 0 | AD2: 0 | AE2: 0 | AF2: 0 | AG2: 0 | AH2: 0 | AI2: 0 | AJ2: ='Row data'!$S2+'Row data'!$T2+'Row data'!$U2+'Row data'!$W2+'Row data'!$X2+'Row data'!$Y2+'Row data'!$Z2+'Row data'!$AA2+'Row data'!$AB2+'Row data'!$AD2-'Row data'!$AC2-'Row data'!$AE2-'Row data'!$AF2-'Row data'!$AG2-'Row data'!$AH2-'Row data'!$AI2 -> 16305 | AK2: 16305 | AL2: 0
A3: 2 | B3: ABC Company Ltd. | C3: 7835403 | D3: Abir | E3: Production | F3: Fabric Tearing | G3: Head Fitter | H3: 9993201000357870 | I3: 44485 | J3: 44867 | K3: =YEAR('Row data'!$J3) -> 2022 | L3: 28431 | M3: =IF('Row data'!$J3="",DATEDIF('Row data'!$L3,TODAY(),"y"),"0") -> 0 | N3: M | O3: N | P3: Staff | Q3: 32700 | R3: 32700 | S3: 19620 | T3: 9810 | U3: 1308 | V3: 981 | W3: 0 | X3: 0 | Y3: 981 | Z3: 981 | AA3: 0 | AB3: 0 | AC3: 0 | AD3: 0 | AE3: 0 | AF3: 0 | AG3: 0 | AH3: 0 | AI3: 0 | AJ3: ='Row data'!$S3+'Row data'!$T3+'Row data'!$U3+'Row data'!$W3+'Row data'!$X3+'Row data'!$Y3+'Row data'!$Z3+'Row data'!$AA3+'Row data'!$AB3+'Row data'!$AD3-'Row data'!$AC3-'Row data'!$AE3-'Row data'!$AF3-'Row data'!$AG3-'Row data'!$AH3-'Row data'!$AI3 -> 32700 | AK3: 32700 | AL3: 0
A4: 3 | B4: ABC Company Ltd. | C4: 8538860 | D4: Ahsan | E4: Production | F4: Fabric Tearing | G4: Assistant | H4: 703204000030529 | I4: 43996 | J4: 44562 | K4: =YEAR('Row data'!$J4) -> 2022 | L4: 32874 | M4: =IF('Row data'!$J4="",DATEDIF('Row data'!$L4,TODAY(),"y"),"0") -> 0 | N4: M | O4: N | P4: Staff | Q4: 16351 | R4: 16024 | S4: 9810 | T4: 4905 | U4: 654 | V4: 491 | W4: 0 | X4: 0 | Y4: 491 | Z4: 491 | AA4: 0 | AB4: 0 | AC4: -327 | AD4: 0 | AE4: 0 | AF4: 0 | AG4: 0 | AH4: 0 | AI4: 0 | AJ4: ='Row data'!$S4+'Row data'!$T4+'Row data'!$U4+'Row data'!$W4+'Row data'!$X4+'Row data'!$Y4+'Row data'!$Z4+'Row data'!$AA4+'Row data'!$AB4+'Row data'!$AD4-'Row data'!$AC4-'Row data'!$AE4-'Row data'!$AF4-'Row data'!$AG4-'Row data'!$AH4-'Row data'!$AI4 -> 16678 | AK4: 16024 | AL4: 0
A5: 4 | B5: ABC Company Ltd. | C5: 8627585 | D5: Akash | E5: Production | F5: Fabric Tearing | G5: Senior Fitter | H5: 9993204000003280 | I5: 44531 | L5: 33238 | M5: =IF('Row data'!$J5="",DATEDIF('Row data'!$L5,TODAY(),"y"),"0") -> 35 | N5: M | O5: N | P5: Staff | Q5: 24526 | R5: 24526 | S5: 14715 | T5: 7358 | U5: 981 | V5: 736 | W5: 0 | X5: 0 | Y5: 736 | Z5: 736 | AA5: 0 | AB5: 0 | AC5: 0 | AD5: 0 | AE5: 0 | AF5: 0 | AG5: 0 | AH5: 0 | AI5: 0 | AJ5: ='Row data'!$S5+'Row data'!$T5+'Row data'!$U5+'Row data'!$W5+'Row data'!$X5+'Row data'!$Y5+'Row data'!$Z5+'Row data'!$AA5+'Row data'!$AB5+'Row data'!$AD5-'Row data'!$AC5-'Row data'!$AE5-'Row data'!$AF5-'Row data'!$AG5-'Row data'!$AH5-'Row data'!$AI5 -> 24526 | AK5: 24526 | AL5: 0
A6: 5 | B6: ABC Company Ltd. | C6: 9077918 | D6: Alamgir | E6: Production | F6: Heatbond | G6: Shift Engineer | H6: 9993204000003430 | I6: 44516 | L6: 34699 | M6: =IF('Row data'!$J6="",DATEDIF('Row data'!$L6,TODAY(),"y"),"0") -> 31 | N6: M | O6: N | P6: Staff | Q6: 27251 | R6: 27251 | S6: 16350 | T6: 8175 | U6: 1090 | V6: 818 | W6: 0 | X6: 0 | Y6: 818 | Z6: 818 | AA6: 0 | AB6: 0 | AC6: 0 | AD6: 0 | AE6: 0 | AF6: 0 | AG6: 0 | AH6: 0 | AI6: 0 | AJ6: ='Row data'!$S6+'Row data'!$T6+'Row data'!$U6+'Row data'!$W6+'Row data'!$X6+'Row data'!$Y6+'Row data'!$Z6+'Row data'!$AA6+'Row data'!$AB6+'Row data'!$AD6-'Row data'!$AC6-'Row data'!$AE6-'Row data'!$AF6-'Row data'!$AG6-'Row data'!$AH6-'Row data'!$AI6 -> 27251 | AK6: 27251 | AL6: 0
A7: 6 | B7: ABC Company Ltd. | C7: 6259828 | D7: Alif | E7: Production | F7: Heatbond | G7: Shift Engineer | H7: 9993204000003420 | I7: 44516 | L7: 35632 | M7: =IF('Row data'!$J7="",DATEDIF('Row data'!$L7,TODAY(),"y"),"0") -> 29 | N7: M | O7: N | P7: Staff | Q7: 26160 | R7: 26160 | S7: 15696 | T7: 7848 | U7: 1046 | V7: 785 | W7: 0 | X7: 0 | Y7: 785 | Z7: 785 | AA7: 0 | AB7: 0 | AC7: 0 | AD7: 0 | AE7: 0 | AF7: 0 | AG7: 0 | AH7: 0 | AI7: 0 | AJ7: ='Row data'!$S7+'Row data'!$T7+'Row data'!$U7+'Row data'!$W7+'Row data'!$X7+'Row data'!$Y7+'Row data'!$Z7+'Row data'!$AA7+'Row data'!$AB7+'Row data'!$AD7-'Row data'!$AC7-'Row data'!$AE7-'Row data'!$AF7-'Row data'!$AG7-'Row data'!$AH7-'Row data'!$AI7 -> 26160 | AK7: 26160 | AL7: 0
A8: 7 | B8: ABC Company Ltd. | C8: 9833929 | D8: Aminul | E8: Production | F8: Heatbond | G8: Senior Supervisor | H8: 703204000030573 | I8: 36968 | J8: 44562 | K8: =YEAR('Row data'!$J8) -> 2022 | L8: 30713 | M8: =IF('Row data'!$J8="",DATEDIF('Row data'!$L8,TODAY(),"y"),"0") -> 0 | N8: M | O8: N | P8: Staff | Q8: 32700 | R8: 32700 | S8: 19620 | T8: 9810 | U8: 1308 | V8: 981 | W8: 0 | X8: 0 | Y8: 981 | Z8: 981 | AA8: 0 | AB8: 0 | AC8: 0 | AD8: 0 | AE8: 0 | AF8: 0 | AG8: 15000 | AH8: 0 | AI8: 0 | AJ8: ='Row data'!$S8+'Row data'!$T8+'Row data'!$U8+'Row data'!$W8+'Row data'!$X8+'Row data'!$Y8+'Row data'!$Z8+'Row data'!$AA8+'Row data'!$AB8+'Row data'!$AD8-'Row data'!$AC8-'Row data'!$AE8-'Row data'!$AF8-'Row data'!$AG8-'Row data'!$AH8-'Row data'!$AI8 -> 17700 | AK8: 17700 | AL8: 0
A9: 8 | B9: ABC Company Ltd. | C9: 7400970 | D9: Anik | E9: Utility & Maintenance | F9: Electrical | G9: Junior Executive | H9: 9993204000003300 | I9: 44721 | L9: 36204 | M9: =IF('Row data'!$J9="",DATEDIF('Row data'!$L9,TODAY(),"y"),"0") -> 27 | N9: M | O9: N | P9: Staff | Q9: 16351 | R9: 16351 | S9: 9810 | T9: 4905 | U9: 654 | V9: 491 | W9: 0 | X9: 0 | Y9: 491 | Z9: 491 | AA9: 0 | AB9: 0 | AC9: 0 | AD9: 0 | AE9: 0 | AF9: 0 | AG9: 0 | AH9: 0 | AI9: 0 | AJ9: ='Row data'!$S9+'Row data'!$T9+'Row data'!$U9+'Row data'!$W9+'Row data'!$X9+'Row data'!$Y9+'Row data'!$Z9+'Row data'!$AA9+'Row data'!$AB9+'Row data'!$AD9-'Row data'!$AC9-'Row data'!$AE9-'Row data'!$AF9-'Row data'!$AG9-'Row data'!$AH9-'Row data'!$AI9 -> 16351 | AK9: 16351 | AL9: 0
A10: 9 | B10: ABC Textile Ltd. | C10: 5912367 | D10: Anisur | E10: Admin | F10: Canteen | G10: Assistant Cook | H10: 703204000030538 | I10: 44765 | L10: 25993 | M10: =IF('Row data'!$J10="",DATEDIF('Row data'!$L10,TODAY(),"y"),"0") -> 55 | N10: F | O10: N | P10: Staff | Q10: 16197 | R10: 16197 | S10: 9718 | T10: 4859 | U10: 648 | V10: 486 | W10: 0 | X10: 0 | Y10: 486 | Z10: 486 | AA10: 0 | AB10: 0 | AC10: 0 | AD10: 0 | AE10: 0 | AF10: 0 | AG10: 0 | AH10: 0 | AI10: 0 | AJ10: ='Row data'!$S10+'Row data'!$T10+'Row data'!$U10+'Row data'!$W10+'Row data'!$X10+'Row data'!$Y10+'Row data'!$Z10+'Row data'!$AA10+'Row data'!$AB10+'Row data'!$AD10-'Row data'!$AC10-'Row data'!$AE10-'Row data'!$AF10-'Row data'!$AG10-'Row data'!$AH10-'Row data'!$AI10 -> 16197 | AK10: 16197 | AL10: 0
A11: 10 | B11: ABC Textile Ltd. | C11: 9402867 | D11: Arif | E11: Admin | F11: Canteen | G11: Assistant Cook | H11: 703204000030981 | I11: 44784 | L11: 26689 | M11: =IF('Row data'!$J11="",DATEDIF('Row data'!$L11,TODAY(),"y"),"0") -> 53 | N11: F | O11: N | P11: Staff | Q11: 16197 | R11: 16197 | S11: 9718 | T11: 4859 | U11: 648 | V11: 486 | W11: 0 | X11: 0 | Y11: 486 | Z11: 486 | AA11: 0 | AB11: 0 | AC11: 0 | AD11: 0 | AE11: 0 | AF11: 0 | AG11: 0 | AH11: 0 | AI11: 0 | AJ11: ='Row data'!$S11+'Row data'!$T11+'Row data'!$U11+'Row data'!$W11+'Row data'!$X11+'Row data'!$Y11+'Row data'!$Z11+'Row data'!$AA11+'Row data'!$AB11+'Row data'!$AD11-'Row data'!$AC11-'Row data'!$AE11-'Row data'!$AF11-'Row data'!$AG11-'Row data'!$AH11-'Row data'!$AI11 -> 16197 | AK11: 16197 | AL11: 0
A12: 11 | B12: ABC Textile Ltd. | C12: 8167313 | D12: Ashfaq | E12: Admin | F12: Canteen | G12: Assistant | H12: 9993204000004140 | I12: 44501 | L12: 36178 | M12: =IF('Row data'!$J12="",DATEDIF('Row data'!$L12,TODAY(),"y"),"0") -> 27 | N12: M | O12: N | P12: Staff | Q12: 16260 | R12: 14260 | S12: 9756 | T12: 4878 | U12: 650 | V12: 488 | W12: 0 | X12: 0 | Y12: 488 | Z12: 488 | AA12: 0 | AB12: 0 | AC12: -2000 | AD12: 0 | AE12: 0 | AF12: 0 | AG12: 0 | AH12: 0 | AI12: 0 | AJ12: ='Row data'!$S12+'Row data'!$T12+'Row data'!$U12+'Row data'!$W12+'Row data'!$X12+'Row data'!$Y12+'Row data'!$Z12+'Row data'!$AA12+'Row data'!$AB12+'Row data'!$AD12-'Row data'!$AC12-'Row data'!$AE12-'Row data'!$AF12-'Row data'!$AG12-'Row data'!$AH12-'Row data'!$AI12 -> 18260 | AK12: 14260 | AL12: 0
A13: 12 | B13: ABC Textile Ltd. | C13: 7225567 | D13: Asif | E13: Admin | F13: Canteen | G13: Assistant Cook | H13: 9993204000004140 | I13: 45185 | L13: 28255 | M13: =IF('Row data'!$J13="",DATEDIF('Row data'!$L13,TODAY(),"y"),"0") -> 49 | N13: F | O13: N | P13: Staff | Q13: 15976 | R13: 15976 | S13: 9586 | T13: 4793 | U13: 639 | V13: 479 | W13: 0 | X13: 0 | Y13: 479 | Z13: 479 | AA13: 0 | AB13: 0 | AC13: 0 | AD13: 0 | AE13: 0 | AF13: 0 | AG13: 0 | AH13: 0 | AI13: 0 | AJ13: ='Row data'!$S13+'Row data'!$T13+'Row data'!$U13+'Row data'!$W13+'Row data'!$X13+'Row data'!$Y13+'Row data'!$Z13+'Row data'!$AA13+'Row data'!$AB13+'Row data'!$AD13-'Row data'!$AC13-'Row data'!$AE13-'Row data'!$AF13-'Row data'!$AG13-'Row data'!$AH13-'Row data'!$AI13 -> 15976 | AK13: 15976 | AL13: 0
A14: 13 | B14: ABC Textile Ltd. | C14: 8864098 | D14: Aziz | E14: Admin | F14: Canteen | G14: Cook | H14: 9993201000060010 | I14: 38261 | L14: 30746 | M14: =IF('Row data'!$J14="",DATEDIF('Row data'!$L14,TODAY(),"y"),"0") -> 42 | N14: M | O14: N | P14: Staff | Q14: 33791 | R14: 33791 | S14: 20274 | T14: 10137 | U14: 1352 | V14: 1014 | W14: 0 | X14: 0 | Y14: 1014 | Z14: 1014 | AA14: 0 | AB14: 0 | AC14: 0 | AD14: 0 | AE14: 0 | AF14: 0 | AG14: 0 | AH14: 0 | AI14: 0 | AJ14: ='Row data'!$S14+'Row data'!$T14+'Row data'!$U14+'Row data'!$W14+'Row data'!$X14+'Row data'!$Y14+'Row data'!$Z14+'Row data'!$AA14+'Row data'!$AB14+'Row data'!$AD14-'Row data'!$AC14-'Row data'!$AE14-'Row data'!$AF14-'Row data'!$AG14-'Row data'!$AH14-'Row data'!$AI14 -> 33791 | AK14: 33791 | AL14: 0
A15: 14 | B15: ABC Textile Ltd. | C15: 6516432 | D15: Badrul | E15: Admin | F15: Canteen | G15: Assistant Cook | I15: 44257 | L15: 32874 | M15: =IF('Row data'!$J15="",DATEDIF('Row data'!$L15,TODAY(),"y"),"0") -> 36 | N15: F | O15: N | P15: Staff | Q15: 15976 | R15: 15976 | S15: 9586 | T15: 4793 | U15: 639 | V15: 479 | W15: 0 | X15: 0 | Y15: 479 | Z15: 479 | AA15: 0 | AB15: 0 | AC15: 0 | AD15: 0 | AE15: 0 | AF15: 0 | AG15: 0 | AH15: 0 | AI15: 0 | AJ15: ='Row data'!$S15+'Row data'!$T15+'Row data'!$U15+'Row data'!$W15+'Row data'!$X15+'Row data'!$Y15+'Row data'!$Z15+'Row data'!$AA15+'Row data'!$AB15+'Row data'!$AD15-'Row data'!$AC15-'Row data'!$AE15-'Row data'!$AF15-'Row data'!$AG15-'Row data'!$AH15-'Row data'!$AI15 -> 15976 | AK15: 15976 | AL15: 0
A16: 15 | B16: ABC Textile Ltd. | C16: 7580318 | D16: Bashir | E16: Admin | F16: Factory Affairs | G16: Deputy General Manager | H16: 563201000085448 | I16: 44378 | J16: 44905 | K16: =YEAR('Row data'!$J16) -> 2022 | L16: 28469 | M16: =IF('Row data'!$J16="",DATEDIF('Row data'!$L16,TODAY(),"y"),"0") -> 0 | N16: M | O16: N | P16: Staff | Q16: 135000 | R16: 135000 | S16: 81000 | T16: 40500 | U16: 5400 | V16: 4050 | W16: 0 | X16: 0 | Y16: 4050 | Z16: 4050 | AA16: 0 | AB16: 0 | AC16: 0 | AD16: 0 | AE16: 0 | AF16: 0 | AG16: 0 | AH16: 3000 | AI16: 0 | AJ16: ='Row data'!$S16+'Row data'!$T16+'Row data'!$U16+'Row data'!$W16+'Row data'!$X16+'Row data'!$Y16+'Row data'!$Z16+'Row data'!$AA16+'Row data'!$AB16+'Row data'!$AD16-'Row data'!$AC16-'Row data'!$AE16-'Row data'!$AF16-'Row data'!$AG16-'Row data'!$AH16-'Row data'!$AI16 -> 132000 | AK16: 132000 | AL16: 0
A17: 16 | B17: ABC Textile Ltd. | C17: 7769663 | D17: Belal | E17: Admin | F17: Security | G17: Lady Checker | H17: 9993204000010980 | I17: 45701 | L17: 35796 | M17: =IF('Row data'!$J17="",DATEDIF('Row data'!$L17,TODAY(),"y"),"0") -> 28 | N17: F | O17: N | P17: Staff | Q17: 14300 | R17: 8171 | S17: 8580 | T17: 4290 | U17: 572 | V17: 429 | W17: 0 | X17: 0 | Y17: 429 | Z17: 429 | AA17: 0 | AB17: 0 | AC17: 0 | AD17: 0 | AE17: 6129 | AF17: 0 | AG17: 0 | AH17: 0 | AI17: 0 | AJ17: ='Row data'!$S17+'Row data'!$T17+'Row data'!$U17+'Row data'!$W17+'Row data'!$X17+'Row data'!$Y17+'Row data'!$Z17+'Row data'!$AA17+'Row data'!$AB17+'Row data'!$AD17-'Row data'!$AC17-'Row data'!$AE17-'Row data'!$AF17-'Row data'!$AG17-'Row data'!$AH17-'Row data'!$AI17 -> 8171 | AK17: 8171 | AL17: 0
A18: 17 | B18: ABC Textile Ltd. | C18: 8771000 | D18: Fahim | E18: Admin | F18: Supports | G18: Loader | H18: 9993204000010070 | I18: 44761 | L18: 34570 | M18: =IF('Row data'!$J18="",DATEDIF('Row data'!$L18,TODAY(),"y"),"0") -> 32 | N18: M | O18: N | P18: Staff | Q18: 15931 | R18: 15931 | S18: 9559 | T18: 4779 | U18: 637 | V18: 478 | W18: 0 | X18: 0 | Y18: 478 | Z18: 478 | AA18: 0 | AB18: 0 | AC18: 0 | AD18: 0 | AE18: 0 | AF18: 0 | AG18: 0 | AH18: 0 | AI18: 0 | AJ18: ='Row data'!$S18+'Row data'!$T18+'Row data'!$U18+'Row data'!$W18+'Row data'!$X18+'Row data'!$Y18+'Row data'!$Z18+'Row data'!$AA18+'Row data'!$AB18+'Row data'!$AD18-'Row data'!$AC18-'Row data'!$AE18-'Row data'!$AF18-'Row data'!$AG18-'Row data'!$AH18-'Row data'!$AI18 -> 15931 | AK18: 15931 | AL18: 0
A19: 18 | B19: ABC Textile Ltd. | C19: 8569356 | D19: Farhan | E19: Admin | F19: Supports | G19: Loader | H19: 9993204000009970 | I19: 44761 | L19: 26718 | M19: =IF('Row data'!$J19="",DATEDIF('Row data'!$L19,TODAY(),"y"),"0") -> 53 | N19: M | O19: N | P19: Staff | Q19: 15931 | R19: 15931 | S19: 9559 | T19: 4779 | U19: 637 | V19: 478 | W19: 0 | X19: 0 | Y19: 478 | Z19: 478 | AA19: 0 | AB19: 0 | AC19: 0 | AD19: 0 | AE19: 0 | AF19: 0 | AG19: 0 | AH19: 0 | AI19: 0 | AJ19: ='Row data'!$S19+'Row data'!$T19+'Row data'!$U19+'Row data'!$W19+'Row data'!$X19+'Row data'!$Y19+'Row data'!$Z19+'Row data'!$AA19+'Row data'!$AB19+'Row data'!$AD19-'Row data'!$AC19-'Row data'!$AE19-'Row data'!$AF19-'Row data'!$AG19-'Row data'!$AH19-'Row data'!$AI19 -> 15931 | AK19: 15931 | AL19: 0
A20: 19 | B20: ABC Textile Ltd. | C20: 9779338 | D20: Faruk | E20: Admin | F20: Supports | G20: Loader | H20: 9993204000010400 | I20: 45171 | L20: 31413 | M20: =IF('Row data'!$J20="",DATEDIF('Row data'!$L20,TODAY(),"y"),"0") -> 40 | N20: M | O20: N | P20: Staff | Q20: 15931 | R20: 15590 | S20: 9559 | T20: 4779 | U20: 637 | V20: 478 | W20: 0 | X20: 0 | Y20: 478 | Z20: 478 | AA20: 0 | AB20: 0 | AC20: 0 | AD20: 0 | AE20: 341 | AF20: 0 | AG20: 0 | AH20: 0 | AI20: 0 | AJ20: ='Row data'!$S20+'Row data'!$T20+'Row data'!$U20+'Row data'!$W20+'Row data'!$X20+'Row data'!$Y20+'Row data'!$Z20+'Row data'!$AA20+'Row data'!$AB20+'Row data'!$AD20-'Row data'!$AC20-'Row data'!$AE20-'Row data'!$AF20-'Row data'!$AG20-'Row data'!$AH20-'Row data'!$AI20 -> 15590 | AK20: 15590 | AL20: 0
A21: 20 | B21: ABC Textile Ltd. | C21: 5974872 | D21: Firoz | E21: Admin | F21: Supports | G21: Loader | H21: 9993204000010440 | I21: 44052 | L21: 30185 | M21: =IF('Row data'!$J21="",DATEDIF('Row data'!$L21,TODAY(),"y"),"0") -> 44 | N21: M | O21: N | P21: Staff | Q21: 16031 | R21: 16031 | S21: 9619 | T21: 4809 | U21: 641 | V21: 481 | W21: 0 | X21: 0 | Y21: 481 | Z21: 481 | AA21: 0 | AB21: 0 | AC21: 0 | AD21: 0 | AE21: 0 | AF21: 0 | AG21: 0 | AH21: 0 | AI21: 0 | AJ21: ='Row data'!$S21+'Row data'!$T21+'Row data'!$U21+'Row data'!$W21+'Row data'!$X21+'Row data'!$Y21+'Row data'!$Z21+'Row data'!$AA21+'Row data'!$AB21+'Row data'!$AD21-'Row data'!$AC21-'Row data'!$AE21-'Row data'!$AF21-'Row data'!$AG21-'Row data'!$AH21-'Row data'!$AI21 -> 16031 | AK21: 16031 | AL21: 0
A22: 21 | B22: ABC Textile Ltd. | C22: 5341375 | D22: Habib | E22: Admin | F22: Supports | G22: Loader | H22: 9993204000010490 | I22: 43282 | J22: 44854 | K22: =YEAR('Row data'!$J22) -> 2022 | L22: 28418 | M22: =IF('Row data'!$J22="",DATEDIF('Row data'!$L22,TODAY(),"y"),"0") -> 0 | N22: M | O22: N | P22: Staff | Q22: 16231 | R22: 16231 | S22: 9739 | T22: 4869 | U22: 649 | V22: 487 | W22: 0 | X22: 0 | Y22: 487 | Z22: 487 | AA22: 0 | AB22: 0 | AC22: 0 | AD22: 0 | AE22: 0 | AF22: 0 | AG22: 0 | AH22: 0 | AI22: 0 | AJ22: ='Row data'!$S22+'Row data'!$T22+'Row data'!$U22+'Row data'!$W22+'Row data'!$X22+'Row data'!$Y22+'Row data'!$Z22+'Row data'!$AA22+'Row data'!$AB22+'Row data'!$AD22-'Row data'!$AC22-'Row data'!$AE22-'Row data'!$AF22-'Row data'!$AG22-'Row data'!$AH22-'Row data'!$AI22 -> 16231 | AK22: 16231 | AL22: 0
A23: 22 | B23: ABC Textile Ltd. | C23: 8755179 | D23: Hafiz | E23: Admin | F23: Vehicle Management | G23: Driver | H23: 9993204000004970 | I23: 45598 | J23: 44562 | K23: =YEAR('Row data'!$J23) -> 2022 | L23: 32852 | M23: =IF('Row data'!$J23="",DATEDIF('Row data'!$L23,TODAY(),"y"),"0") -> 0 | N23: M | O23: N | P23: Staff | Q23: 18000 | R23: 13371 | S23: 10800 | T23: 5400 | U23: 720 | V23: 540 | W23: 0 | X23: 0 | Y23: 540 | Z23: 540 | AA23: 0 | AB23: 0 | AC23: 0 | AD23: 0 | AE23: 4629 | AF23: 0 | AG23: 0 | AH23: 0 | AI23: 10 | AJ23: ='Row data'!$S23+'Row data'!$T23+'Row data'!$U23+'Row data'!$W23+'Row data'!$X23+'Row data'!$Y23+'Row data'!$Z23+'Row data'!$AA23+'Row data'!$AB23+'Row data'!$AD23-'Row data'!$AC23-'Row data'!$AE23-'Row data'!$AF23-'Row data'!$AG23-'Row data'!$AH23-'Row data'!$AI23 -> 13361 | AK23: 0 | AL23: 13361
A24: 23 | B24: ABC Textile Ltd. | C24: 6841704 | D24: Halim | E24: Admin | F24: Vehicle Management | G24: Driver | H24: 703204000030835 | I24: 44121 | L24: 32660 | M24: =IF('Row data'!$J24="",DATEDIF('Row data'!$L24,TODAY(),"y"),"0") -> 37 | N24: M | O24: N | P24: Staff | Q24: 21256 | R24: 20301 | S24: 12753 | T24: 6377 | U24: 850 | V24: 638 | W24: 0 | X24: 0 | Y24: 638 | Z24: 638 | AA24: 0 | AB24: 0 | AC24: -500 | AD24: 0 | AE24: 0 | AF24: 455 | AG24: 0 | AH24: 0 | AI24: 0 | AJ24: ='Row data'!$S24+'Row data'!$T24+'Row data'!$U24+'Row data'!$W24+'Row data'!$X24+'Row data'!$Y24+'Row data'!$Z24+'Row data'!$AA24+'Row data'!$AB24+'Row data'!$AD24-'Row data'!$AC24-'Row data'!$AE24-'Row data'!$AF24-'Row data'!$AG24-'Row data'!$AH24-'Row data'!$AI24 -> 21301 | AK24: 20301 | AL24: 0
A25: 24 | B25: ABC Textile Ltd. | C25: 9572996 | D25: Hasan | E25: Admin | F25: Vehicle Management | G25: Driver | H25: 703204000030460 | I25: 44853 | L25: 32549 | M25: =IF('Row data'!$J25="",DATEDIF('Row data'!$L25,TODAY(),"y"),"0") -> 37 | N25: M | O25: N | P25: Staff | Q25: 22496 | R25: 22496 | S25: 13497 | T25: 6749 | U25: 900 | V25: 675 | W25: 0 | X25: 0 | Y25: 675 | Z25: 675 | AA25: 0 | AB25: 0 | AC25: 0 | AD25: 0 | AE25: 0 | AF25: 0 | AG25: 0 | AH25: 0 | AI25: 0 | AJ25: ='Row data'!$S25+'Row data'!$T25+'Row data'!$U25+'Row data'!$W25+'Row data'!$X25+'Row data'!$Y25+'Row data'!$Z25+'Row data'!$AA25+'Row data'!$AB25+'Row data'!$AD25-'Row data'!$AC25-'Row data'!$AE25-'Row data'!$AF25-'Row data'!$AG25-'Row data'!$AH25-'Row data'!$AI25 -> 22496 | AK25: 22496 | AL25: 0
A26: 25 | B26: ABC Textile Ltd. | C26: 9836296 | D26: Helal | E26: Admin | F26: Vehicle Management | G26: Assistant Forklift Driver | H26: 703204000031248 | I26: 44501 | L26: 27740 | M26: =IF('Row data'!$J26="",DATEDIF('Row data'!$L26,TODAY(),"y"),"0") -> 50 | N26: M | O26: N | P26: Staff | Q26: 21951 | R26: 21951 | S26: 13170 | T26: 6585 | U26: 878 | V26: 659 | W26: 0 | X26: 0 | Y26: 659 | Z26: 659 | AA26: 0 | AB26: 0 | AC26: 0 | AD26: 0 | AE26: 0 | AF26: 0 | AG26: 0 | AH26: 0 | AI26: 0 | AJ26: ='Row data'!$S26+'Row data'!$T26+'Row data'!$U26+'Row data'!$W26+'Row data'!$X26+'Row data'!$Y26+'Row data'!$Z26+'Row data'!$AA26+'Row data'!$AB26+'Row data'!$AD26-'Row data'!$AC26-'Row data'!$AE26-'Row data'!$AF26-'Row data'!$AG26-'Row data'!$AH26-'Row data'!$AI26 -> 21951 | AK26: 21951 | AL26: 0
A27: 26 | B27: ABC Textile Ltd. | C27: 5420911 | D27: Hossain | E27: Delivery | F27: Delivery | G27: Trainee Officer | H27: 703204000031237 | I27: 44807 | L27: 36916 | M27: =IF('Row data'!$J27="",DATEDIF('Row data'!$L27,TODAY(),"y"),"0") -> 25 | N27: M | O27: N | P27: Staff | Q27: 16351 | R27: 16351 | S27: 9810 | T27: 4905 | U27: 654 | V27: 491 | W27: 0 | X27: 0 | Y27: 491 | Z27: 491 | AA27: 0 | AB27: 0 | AC27: 0 | AD27: 0 | AE27: 0 | AF27: 0 | AG27: 0 | AH27: 0 | AI27: 0 | AJ27: ='Row data'!$S27+'Row data'!$T27+'Row data'!$U27+'Row data'!$W27+'Row data'!$X27+'Row data'!$Y27+'Row data'!$Z27+'Row data'!$AA27+'Row data'!$AB27+'Row data'!$AD27-'Row data'!$AC27-'Row data'!$AE27-'Row data'!$AF27-'Row data'!$AG27-'Row data'!$AH27-'Row data'!$AI27 -> 16351 | AK27: 16351 | AL27: 0
A28: 27 | B28: ABC Textile Ltd. | C28: 9713316 | D28: Iftekhar | E28: HR & Compliance | F28: Administration | G28: Asst. Admin Officer | H28: 9993204000003200 | I28: 44573 | L28: 31402 | M28: =IF('Row data'!$J28="",DATEDIF('Row data'!$L28,TODAY(),"y"),"0") -> 40 | N28: M | O28: N | P28: Staff | Q28: 22345 | R28: 22345 | S28: 13407 | T28: 6704 | U28: 894 | V28: 670 | W28: 0 | X28: 0 | Y28: 670 | Z28: 670 | AA28: 0 | AB28: 0 | AC28: 0 | AD28: 0 | AE28: 0 | AF28: 0 | AG28: 0 | AH28: 0 | AI28: 0 | AJ28: ='Row data'!$S28+'Row data'!$T28+'Row data'!$U28+'Row data'!$W28+'Row data'!$X28+'Row data'!$Y28+'Row data'!$Z28+'Row data'!$AA28+'Row data'!$AB28+'Row data'!$AD28-'Row data'!$AC28-'Row data'!$AE28-'Row data'!$AF28-'Row data'!$AG28-'Row data'!$AH28-'Row data'!$AI28 -> 22345 | AK28: 22345 | AL28: 0
A29: 28 | B29: ABC Textile Ltd. | C29: 7034621 | D29: Imran | E29: HR & Compliance | F29: HR | G29: Executive | H29: 9993204000003160 | I29: 43678 | L29: 32752 | M29: =IF('Row data'!$J29="",DATEDIF('Row data'!$L29,TODAY(),"y"),"0") -> 37 | N29: M | O29: N | P29: Staff | Q29: 27251 | R29: 27251 | S29: 16350 | T29: 8175 | U29: 1090 | V29: 818 | W29: 0 | X29: 0 | Y29: 818 | Z29: 818 | AA29: 0 | AB29: 0 | AC29: 0 | AD29: 0 | AE29: 0 | AF29: 0 | AG29: 2500 | AH29: 0 | AI29: 0 | AJ29: ='Row data'!$S29+'Row data'!$T29+'Row data'!$U29+'Row data'!$W29+'Row data'!$X29+'Row data'!$Y29+'Row data'!$Z29+'Row data'!$AA29+'Row data'!$AB29+'Row data'!$AD29-'Row data'!$AC29-'Row data'!$AE29-'Row data'!$AF29-'Row data'!$AG29-'Row data'!$AH29-'Row data'!$AI29 -> 24751 | AK29: 24751 | AL29: 0
A30: 29 | B30: ABC Textile Ltd. | C30: 8555326 | D30: Iqbal | E30: IT | F30: Information Technology | G30: Executive | H30: 9993201000341460 | I30: 44480 | L30: 35431 | M30: =IF('Row data'!$J30="",DATEDIF('Row data'!$L30,TODAY(),"y"),"0") -> 29 | N30: M | O30: N | P30: Staff | Q30: 32700 | R30: 32700 | S30: 19620 | T30: 9810 | U30: 1308 | V30: 981 | W30: 0 | X30: 0 | Y30: 981 | Z30: 981 | AA30: 0 | AB30: 0 | AC30: 0 | AD30: 0 | AE30: 0 | AF30: 0 | AG30: 0 | AH30: 0 | AI30: 0 | AJ30: ='Row data'!$S30+'Row data'!$T30+'Row data'!$U30+'Row data'!$W30+'Row data'!$X30+'Row data'!$Y30+'Row data'!$Z30+'Row data'!$AA30+'Row data'!$AB30+'Row data'!$AD30-'Row data'!$AC30-'Row data'!$AE30-'Row data'!$AF30-'Row data'!$AG30-'Row data'!$AH30-'Row data'!$AI30 -> 32700 | AK30: 32700 | AL30: 0
A31: 30 | B31: ABC Textile Ltd. | C31: 7352540 | D31: Ishtiaq | E31: Production | F31: Andritz Geo | G31: Shift Engineer | H31: 7863241000026650 | I31: 44604 | L31: 33313 | M31: =IF('Row data'!$J31="",DATEDIF('Row data'!$L31,TODAY(),"y"),"0") -> 35 | N31: M | O31: N | P31: Staff | Q31: 34879 | R31: 34879 | S31: 20928 | T31: 10464 | U31: 1395 | V31: 1046 | W31: 0 | X31: 0 | Y31: 1046 | Z31: 1046 | AA31: 0 | AB31: 0 | AC31: 0 | AD31: 0 | AE31: 0 | AF31: 0 | AG31: 0 | AH31: 0 | AI31: 0 | AJ31: ='Row data'!$S31+'Row data'!$T31+'Row data'!$U31+'Row data'!$W31+'Row data'!$X31+'Row data'!$Y31+'Row data'!$Z31+'Row data'!$AA31+'Row data'!$AB31+'Row data'!$AD31-'Row data'!$AC31-'Row data'!$AE31-'Row data'!$AF31-'Row data'!$AG31-'Row data'!$AH31-'Row data'!$AI31 -> 34879 | AK31: 34879 | AL31: 0
A32: 31 | B32: ABC Textile Ltd. | C32: 6659696 | D32: Jakir | E32: Production | F32: Andritz Geo | G32: Shift Engineer | H32: 9993204000003310 | I32: 45241 | L32: 36932 | M32: =IF('Row data'!$J32="",DATEDIF('Row data'!$L32,TODAY(),"y"),"0") -> 25 | N32: M | O32: N | P32: Staff | Q32: 21256 | R32: 21256 | S32: 12753 | T32: 6377 | U32: 850 | V32: 638 | W32: 0 | X32: 0 | Y32: 638 | Z32: 638 | AA32: 0 | AB32: 0 | AC32: 0 | AD32: 0 | AE32: 0 | AF32: 0 | AG32: 0 | AH32: 0 | AI32: 0 | AJ32: ='Row data'!$S32+'Row data'!$T32+'Row data'!$U32+'Row data'!$W32+'Row data'!$X32+'Row data'!$Y32+'Row data'!$Z32+'Row data'!$AA32+'Row data'!$AB32+'Row data'!$AD32-'Row data'!$AC32-'Row data'!$AE32-'Row data'!$AF32-'Row data'!$AG32-'Row data'!$AH32-'Row data'!$AI32 -> 21256 | AK32: 21256 | AL32: 0
A33: 32 | B33: ABC Textile Ltd. | C33: 8252375 | D33: Jalal | E33: Production | F33: Andritz Geo | G33: Trainee Shift Engineer | H33: 9993201000466550 | I33: 43785 | L33: 36393 | M33: =IF('Row data'!$J33="",DATEDIF('Row data'!$L33,TODAY(),"y"),"0") -> 27 | N33: M | O33: N | P33: Staff | Q33: 27251 | R33: 27251 | S33: 16350 | T33: 8175 | U33: 1090 | V33: 818 | W33: 0 | X33: 0 | Y33: 818 | Z33: 818 | AA33: 0 | AB33: 0 | AC33: 0 | AD33: 0 | AE33: 0 | AF33: 0 | AG33: 0 | AH33: 0 | AI33: 0 | AJ33: ='Row data'!$S33+'Row data'!$T33+'Row data'!$U33+'Row data'!$W33+'Row data'!$X33+'Row data'!$Y33+'Row data'!$Z33+'Row data'!$AA33+'Row data'!$AB33+'Row data'!$AD33-'Row data'!$AC33-'Row data'!$AE33-'Row data'!$AF33-'Row data'!$AG33-'Row data'!$AH33-'Row data'!$AI33 -> 27251 | AK33: 27251 | AL33: 0
A34: 33 | B34: ABC Textile Ltd. | C34: 7953821 | D34: Jahangir | E34: Production | F34: Andritz Geo | G34: Shift Engineer | H34: 9993201000306610 | I34: 44216 | L34: 34428 | M34: =IF('Row data'!$J34="",DATEDIF('Row data'!$L34,TODAY(),"y"),"0") -> 32 | N34: M | O34: N | P34: Staff | Q34: 26787 | R34: 21787 | S34: 16072 | T34: 8036 | U34: 1071 | V34: 804 | W34: 0 | X34: 0 | Y34: 804 | Z34: 804 | AA34: 0 | AB34: 0 | AC34: -5000 | AD34: 0 | AE34: 0 | AF34: 0 | AG34: 0 | AH34: 0 | AI34: 0 | AJ34: ='Row data'!$S34+'Row data'!$T34+'Row data'!$U34+'Row data'!$W34+'Row data'!$X34+'Row data'!$Y34+'Row data'!$Z34+'Row data'!$AA34+'Row data'!$AB34+'Row data'!$AD34-'Row data'!$AC34-'Row data'!$AE34-'Row data'!$AF34-'Row data'!$AG34-'Row data'!$AH34-'Row data'!$AI34 -> 31787 | AK34: 21787 | AL34: 0
A35: 34 | B35: ABC Textile Ltd. | C35: 8949990 | D35: Jahid | E35: Production | F35: Andritz Geo | G35: Sr. Shift Engineer | H35: 9993201000061280 | I35: 43040 | L35: 32969 | M35: =IF('Row data'!$J35="",DATEDIF('Row data'!$L35,TODAY(),"y"),"0") -> 36 | N35: M | O35: N | P35: Staff | Q35: 36461 | R35: 36461 | S35: 21877 | T35: 10938 | U35: 1458 | V35: 1094 | W35: 0 | X35: 0 | Y35: 1094 | Z35: 1094 | AA35: 0 | AB35: 0 | AC35: 0 | AD35: 0 | AE35: 0 | AF35: 0 | AG35: 0 | AH35: 0 | AI35: 0 | AJ35: ='Row data'!$S35+'Row data'!$T35+'Row data'!$U35+'Row data'!$W35+'Row data'!$X35+'Row data'!$Y35+'Row data'!$Z35+'Row data'!$AA35+'Row data'!$AB35+'Row data'!$AD35-'Row data'!$AC35-'Row data'!$AE35-'Row data'!$AF35-'Row data'!$AG35-'Row data'!$AH35-'Row data'!$AI35 -> 36461 | AK35: 36461 | AL35: 0
... A42: 41 | B42: ABC Textile Ltd. | C42: 6776594 | D42: Mahbub | E42: Production | F42: Needle Punch | G42: Supervisor | H42: 9993201000321990 | I42: 44352 | L42: 32051 | M42: =IF('Row data'!$J42="",DATEDIF('Row data'!$L42,TODAY(),"y"),"0") -> 38 | N42: M | O42: N | P42: Staff | Q42: 40875 | R42: 40875 | S42: 24525 | T42: 12263 | U42: 1635 | V42: 1226 | W42: 0 | X42: 0 | Y42: 1226 | Z42: 1226 | AA42: 0 | AB42: 0 | AC42: 0 | AD42: 0 | AE42: 0 | AF42: 0 | AG42: 0 | AH42: 0 | AI42: 0 | AJ42: ='Row data'!$S42+'Row data'!$T42+'Row data'!$U42+'Row data'!$W42+'Row data'!$X42+'Row data'!$Y42+'Row data'!$Z42+'Row data'!$AA42+'Row data'!$AB42+'Row data'!$AD42-'Row data'!$AC42-'Row data'!$AE42-'Row data'!$AF42-'Row data'!$AG42-'Row data'!$AH42-'Row data'!$AI42 -> 40875 | AK42: 40875 | AL42: 0
A43: 42 | B43: ABC Textile Ltd. | C43: 8801301 | D43: Mahdi | E43: Production | F43: Sewing Geo | G43: Assistant Operator | H43: 9993204000006530 | I43: 42409 | J43: 44572 | K43: =YEAR('Row data'!$J43) -> 2022 | L43: 34895 | M43: =IF('Row data'!$J43="",DATEDIF('Row data'!$L43,TODAY(),"y"),"0") -> 0 | N43: M | O43: N | P43: Staff | Q43: 16097 | R43: 16097 | S43: 9658 | T43: 4829 | U43: 644 | V43: 483 | W43: 0 | X43: 0 | Y43: 483 | Z43: 483 | AA43: 0 | AB43: 0 | AC43: 0 | AD43: 0 | AE43: 0 | AF43: 0 | AG43: 0 | AH43: 0 | AI43: 0 | AJ43: ='Row data'!$S43+'Row data'!$T43+'Row data'!$U43+'Row data'!$W43+'Row data'!$X43+'Row data'!$Y43+'Row data'!$Z43+'Row data'!$AA43+'Row data'!$AB43+'Row data'!$AD43-'Row data'!$AC43-'Row data'!$AE43-'Row data'!$AF43-'Row data'!$AG43-'Row data'!$AH43-'Row data'!$AI43 -> 16097 | AK43: 16097 | AL43: 0
A44: 43 | B44: ABC Textile Ltd. | C44: 9717095 | D44: Mahfuz | E44: Production | F44: Sewing Geo | G44: Quality Inspector | H44: 703204000030493 | I44: 43179 | L44: 35648 | M44: =IF('Row data'!$J44="",DATEDIF('Row data'!$L44,TODAY(),"y"),"0") -> 29 | N44: M | O44: N | P44: Staff | Q44: 16532 | R44: 16178 | S44: 9919 | T44: 4960 | U44: 661 | V44: 496 | W44: 0 | X44: 0 | Y44: 496 | Z44: 496 | AA44: 0 | AB44: 0 | AC44: 0 | AD44: 0 | AE44: 354 | AF44: 0 | AG44: 0 | AH44: 0 | AI44: 0 | AJ44: ='Row data'!$S44+'Row data'!$T44+'Row data'!$U44+'Row data'!$W44+'Row data'!$X44+'Row data'!$Y44+'Row data'!$Z44+'Row data'!$AA44+'Row data'!$AB44+'Row data'!$AD44-'Row data'!$AC44-'Row data'!$AE44-'Row data'!$AF44-'Row data'!$AG44-'Row data'!$AH44-'Row data'!$AI44 -> 16178 | AK44: 16178 | AL44: 0
A45: 44 | B45: ABC Textile Ltd. | C45: 7773498 | D45: Mamun | E45: Production | F45: Sewing Geo | G45: Assistant Supervisor | H45: 703204000030518 | I45: 42448 | L45: 34745 | M45: =IF('Row data'!$J45="",DATEDIF('Row data'!$L45,TODAY(),"y"),"0") -> 31 | N45: M | O45: N | P45: Staff | Q45: 22891 | R45: 22891 | S45: 13734 | T45: 6867 | U45: 916 | V45: 687 | W45: 0 | X45: 0 | Y45: 687 | Z45: 687 | AA45: 0 | AB45: 0 | AC45: 0 | AD45: 0 | AE45: 0 | AF45: 0 | AG45: 0 | AH45: 0 | AI45: 0 | AJ45: ='Row data'!$S45+'Row data'!$T45+'Row data'!$U45+'Row data'!$W45+'Row data'!$X45+'Row data'!$Y45+'Row data'!$Z45+'Row data'!$AA45+'Row data'!$AB45+'Row data'!$AD45-'Row data'!$AC45-'Row data'!$AE45-'Row data'!$AF45-'Row data'!$AG45-'Row data'!$AH45-'Row data'!$AI45 -> 22891 | AK45: 22891 | AL45: 0
A46: 45 | B46: ABC Textile Ltd. | C46: 6974260 | D46: Maruf | E46: Production | F46: Sewing Geo | G46: Quality Inspector | H46: 703204000030970 | I46: 43138 | L46: 36239 | M46: =IF('Row data'!$J46="",DATEDIF('Row data'!$L46,TODAY(),"y"),"0") -> 27 | N46: M | O46: N | P46: Staff | Q46: 16532 | R46: 16532 | S46: 9919 | T46: 4960 | U46: 661 | V46: 496 | W46: 0 | X46: 0 | Y46: 496 | Z46: 496 | AA46: 0 | AB46: 0 | AC46: 0 | AD46: 0 | AE46: 0 | AF46: 0 | AG46: 0 | AH46: 0 | AI46: 0 | AJ46: ='Row data'!$S46+'Row data'!$T46+'Row data'!$U46+'Row data'!$W46+'Row data'!$X46+'Row data'!$Y46+'Row data'!$Z46+'Row data'!$AA46+'Row data'!$AB46+'Row data'!$AD46-'Row data'!$AC46-'Row data'!$AE46-'Row data'!$AF46-'Row data'!$AG46-'Row data'!$AH46-'Row data'!$AI46 -> 16532 | AK46: 16532 | AL46: 0
A47: 46 | B47: ABC Textile Ltd. | C47: 9531431 | D47: Mehedi | E47: Production | F47: Sewing Geo | G47: Supervisor | H47: 9993201000307840 | I47: 42064 | L47: 30669 | M47: =IF('Row data'!$J47="",DATEDIF('Row data'!$L47,TODAY(),"y"),"0") -> 42 | N47: M | O47: N | P47: Staff | Q47: 25070 | R47: 25070 | S47: 15042 | T47: 7521 | U47: 1003 | V47: 752 | W47: 0 | X47: 0 | Y47: 752 | Z47: 752 | AA47: 0 | AB47: 0 | AC47: 0 | AD47: 0 | AE47: 0 | AF47: 0 | AG47: 0 | AH47: 0 | AI47: 0 | AJ47: ='Row data'!$S47+'Row data'!$T47+'Row data'!$U47+'Row data'!$W47+'Row data'!$X47+'Row data'!$Y47+'Row data'!$Z47+'Row data'!$AA47+'Row data'!$AB47+'Row data'!$AD47-'Row data'!$AC47-'Row data'!$AE47-'Row data'!$AF47-'Row data'!$AG47-'Row data'!$AH47-'Row data'!$AI47 -> 25070 | AK47: 25070 | AL47: 0
A48: 47 | B48: ABC Textile Ltd. | C48: 7243992 | D48: Minhaj | E48: Production | F48: Sewing Geo | G48: Mechanic | H48: 9993201000060310 | I48: 42140 | L48: 34650 | M48: =IF('Row data'!$J48="",DATEDIF('Row data'!$L48,TODAY(),"y"),"0") -> 31 | N48: M | O48: N | P48: Staff | Q48: 24264 | R48: 24264 | S48: 14558 | T48: 7279 | U48: 971 | V48: 728 | W48: 0 | X48: 0 | Y48: 728 | Z48: 728 | AA48: 0 | AB48: 0 | AC48: 0 | AD48: 0 | AE48: 0 | AF48: 0 | AG48: 0 | AH48: 0 | AI48: 0 | AJ48: ='Row data'!$S48+'Row data'!$T48+'Row data'!$U48+'Row data'!$W48+'Row data'!$X48+'Row data'!$Y48+'Row data'!$Z48+'Row data'!$AA48+'Row data'!$AB48+'Row data'!$AD48-'Row data'!$AC48-'Row data'!$AE48-'Row data'!$AF48-'Row data'!$AG48-'Row data'!$AH48-'Row data'!$AI48 -> 24264 | AK48: 24264 | AL48: 0
A49: 48 | B49: ABC Textile Ltd. | C49: 6758752 | D49: Miraz | E49: Production | F49: Sewing Geo | G49: General Quality Inspector | I49: 45048 | L49: 38364 | M49: =IF('Row data'!$J49="",DATEDIF('Row data'!$L49,TODAY(),"y"),"0") -> 21 | N49: M | O49: N | P49: Staff | Q49: 16048 | R49: 16048 | S49: 9629 | T49: 4815 | U49: 642 | V49: 481 | W49: 0 | X49: 0 | Y49: 481 | Z49: 481 | AA49: 0 | AB49: 0 | AC49: 0 | AD49: 0 | AE49: 0 | AF49: 0 | AG49: 0 | AH49: 0 | AI49: 0 | AJ49: ='Row data'!$S49+'Row data'!$T49+'Row data'!$U49+'Row data'!$W49+'Row data'!$X49+'Row data'!$Y49+'Row data'!$Z49+'Row data'!$AA49+'Row data'!$AB49+'Row data'!$AD49-'Row data'!$AC49-'Row data'!$AE49-'Row data'!$AF49-'Row data'!$AG49-'Row data'!$AH49-'Row data'!$AI49 -> 16048 | AK49: 16048 | AL49: 0
A50: 49 | B50: ABC Textile Ltd. | C50: 6089090 | D50: Mizan | E50: Store | F50: Store | G50: Store Co-Ordinator(Assistant) | H50: 9993204000003320 | I50: 45202 | L50: 32664 | M50: =IF('Row data'!$J50="",DATEDIF('Row data'!$L50,TODAY(),"y"),"0") -> 37 | N50: M | O50: N | P50: Staff | Q50: 17386 | R50: 17212 | S50: 10431 | T50: 5216 | U50: 695 | V50: 522 | W50: 0 | X50: 0 | Y50: 522 | Z50: 522 | AA50: 0 | AB50: 0 | AC50: -174 | AD50: 0 | AE50: 0 | AF50: 0 | AG50: 0 | AH50: 0 | AI50: 0 | AJ50: ='Row data'!$S50+'Row data'!$T50+'Row data'!$U50+'Row data'!$W50+'Row data'!$X50+'Row data'!$Y50+'Row data'!$Z50+'Row data'!$AA50+'Row data'!$AB50+'Row data'!$AD50-'Row data'!$AC50-'Row data'!$AE50-'Row data'!$AF50-'Row data'!$AG50-'Row data'!$AH50-'Row data'!$AI50 -> 17560 | AK50: 17212 | AL50: 0
A51: 50 | B51: ABC Textile Ltd. | C51: 8660049 | D51: Monir | E51: Store | F51: Store | G51: Store Officer | H51: 9993201000063560 | I51: 41597 | J51: 44812 | K51: =YEAR('Row data'!$J51) -> 2022 | L51: 33855 | M51: =IF('Row data'!$J51="",DATEDIF('Row data'!$L51,TODAY(),"y"),"0") -> 0 | N51: M | O51: N | P51: Staff | Q51: 29103 | R51: 25103 | S51: 17462 | T51: 8731 | U51: 1164 | V51: 873 | W51: 0 | X51: 0 | Y51: 873 | Z51: 873 | AA51: 0 | AB51: 0 | AC51: -4000 | AD51: 0 | AE51: 0 | AF51: 0 | AG51: 0 | AH51: 0 | AI51: 0 | AJ51: ='Row data'!$S51+'Row data'!$T51+'Row data'!$U51+'Row data'!$W51+'Row data'!$X51+'Row data'!$Y51+'Row data'!$Z51+'Row data'!$AA51+'Row data'!$AB51+'Row data'!$AD51-'Row data'!$AC51-'Row data'!$AE51-'Row data'!$AF51-'Row data'!$AG51-'Row data'!$AH51-'Row data'!$AI51 -> 33103 | AK51: 25103 | AL51: 0
A52: 51 | B52: ABC Textile Ltd. | C52: 6570653 | D52: Mosharraf | E52: Store | F52: Store | G52: Store Co-Ordinator(Assistant) | H52: 703204000030540 | I52: 43180 | L52: 35765 | M52: =IF('Row data'!$J52="",DATEDIF('Row data'!$L52,TODAY(),"y"),"0") -> 28 | N52: M | O52: N | P52: Staff | Q52: 23001 | R52: 22771 | S52: 13801 | T52: 6900 | U52: 920 | V52: 690 | W52: 0 | X52: 0 | Y52: 690 | Z52: 690 | AA52: 0 | AB52: 0 | AC52: -230 | AD52: 0 | AE52: 0 | AF52: 0 | AG52: 0 | AH52: 0 | AI52: 0 | AJ52: ='Row data'!$S52+'Row data'!$T52+'Row data'!$U52+'Row data'!$W52+'Row data'!$X52+'Row data'!$Y52+'Row data'!$Z52+'Row data'!$AA52+'Row data'!$AB52+'Row data'!$AD52-'Row data'!$AC52-'Row data'!$AE52-'Row data'!$AF52-'Row data'!$AG52-'Row data'!$AH52-'Row data'!$AI52 -> 23231 | AK52: 22771 | AL52: 0
A53: 52 | B53: ABC Textile Ltd. | C53: 6168569 | D53: Mostafa | E53: Utility & Maintenance | F53: Electrical | G53: Shift Engineer | H53: 9993204000009530 | I53: 45696 | L53: 36636 | M53: =IF('Row data'!$J53="",DATEDIF('Row data'!$L53,TODAY(),"y"),"0") -> 26 | N53: M | O53: N | P53: Staff | Q53: 22000 | R53: 16500 | S53: 13200 | T53: 6600 | U53: 880 | V53: 660 | W53: 0 | X53: 0 | Y53: 660 | Z53: 660 | AA53: 0 | AB53: 0 | AC53: 0 | AD53: 0 | AE53: 5500 | AF53: 0 | AG53: 0 | AH53: 0 | AI53: 0 | AJ53: ='Row data'!$S53+'Row data'!$T53+'Row data'!$U53+'Row data'!$W53+'Row data'!$X53+'Row data'!$Y53+'Row data'!$Z53+'Row data'!$AA53+'Row data'!$AB53+'Row data'!$AD53-'Row data'!$AC53-'Row data'!$AE53-'Row data'!$AF53-'Row data'!$AG53-'Row data'!$AH53-'Row data'!$AI53 -> 16500 | AK53: 16500 | AL53: 0
A54: 53 | B54: ABC Textile Ltd. | C54: 5909965 | D54: Muktadir | E54: Utility & Maintenance | F54: Electrical | G54: Junior Executive (Electrical) | H54: 703204000031099 | I54: 44081 | J54: 44831 | K54: =YEAR('Row data'!$J54) -> 2022 | L54: 35065 | M54: =IF('Row data'!$J54="",DATEDIF('Row data'!$L54,TODAY(),"y"),"0") -> 0 | N54: M | O54: N | P54: Staff | Q54: 23654 | R54: 18654 | S54: 14192 | T54: 7096 | U54: 946 | V54: 710 | W54: 0 | X54: 0 | Y54: 710 | Z54: 710 | AA54: 0 | AB54: 0 | AC54: -5000 | AD54: 0 | AE54: 0 | AF54: 0 | AG54: 0 | AH54: 0 | AI54: 0 | AJ54: ='Row data'!$S54+'Row data'!$T54+'Row data'!$U54+'Row data'!$W54+'Row data'!$X54+'Row data'!$Y54+'Row data'!$Z54+'Row data'!$AA54+'Row data'!$AB54+'Row data'!$AD54-'Row data'!$AC54-'Row data'!$AE54-'Row data'!$AF54-'Row data'!$AG54-'Row data'!$AH54-'Row data'!$AI54 -> 28654 | AK54: 18654 | AL54: 0
A55: 54 | B55: ABC Textile Ltd. | C55: 7554976 | D55: Munna | E55: Utility & Maintenance | F55: Electrical | G55: Junior Executive (Electrical) | H55: 9993201000307920 | I55: 44083 | L55: 34344 | M55: =IF('Row data'!$J55="",DATEDIF('Row data'!$L55,TODAY(),"y"),"0") -> 32 | N55: M | O55: N | P55: Staff | Q55: 25070 | R55: 25070 | S55: 15042 | T55: 7521 | U55: 1003 | V55: 752 | W55: 0 | X55: 0 | Y55: 752 | Z55: 752 | AA55: 0 | AB55: 0 | AC55: 0 | AD55: 0 | AE55: 0 | AF55: 0 | AG55: 0 | AH55: 0 | AI55: 0 | AJ55: ='Row data'!$S55+'Row data'!$T55+'Row data'!$U55+'Row data'!$W55+'Row data'!$X55+'Row data'!$Y55+'Row data'!$Z55+'Row data'!$AA55+'Row data'!$AB55+'Row data'!$AD55-'Row data'!$AC55-'Row data'!$AE55-'Row data'!$AF55-'Row data'!$AG55-'Row data'!$AH55-'Row data'!$AI55 -> 25070 | AK55: 25070 | AL55: 0
A56: 55 | B56: ABC Textile Ltd. | C56: 5122456 | D56: Murad | E56: Utility & Maintenance | F56: Electrical | G56: Junior Executive (Electrical) | H56: 9993201000307860 | I56: 44105 | J56: 45697 | K56: =YEAR('Row data'!$J56) -> 2025 | L56: 35833 | M56: =IF('Row data'!$J56="",DATEDIF('Row data'!$L56,TODAY(),"y"),"0") -> 0 | N56: M | O56: N | P56: Staff | Q56: 24700 | R56: 7939 | S56: 14820 | T56: 7410 | U56: 988 | V56: 741 | W56: 0 | X56: 0 | Y56: 741 | Z56: 741 | AA56: 0 | AB56: 0 | AC56: 0 | AD56: 0 | AE56: 16761 | AF56: 0 | AG56: 0 | AH56: 0 | AI56: 10 | AJ56: ='Row data'!$S56+'Row data'!$T56+'Row data'!$U56+'Row data'!$W56+'Row data'!$X56+'Row data'!$Y56+'Row data'!$Z56+'Row data'!$AA56+'Row data'!$AB56+'Row data'!$AD56-'Row data'!$AC56-'Row data'!$AE56-'Row data'!$AF56-'Row data'!$AG56-'Row data'!$AH56-'Row data'!$AI56 -> 7929 | AK56: 0 | AL56: 7929
A57: 56 | B57: ABC Textile Ltd. | C57: 7876756 | D57: Mustafiz | E57: Utility & Maintenance | F57: Electrical | G57: Assistant Electrician | H57: 1343204000011520 | I57: 43807 | L57: 35142 | M57: =IF('Row data'!$J57="",DATEDIF('Row data'!$L57,TODAY(),"y"),"0") -> 30 | N57: M | O57: N | P57: Staff | Q57: 18535 | R57: 18535 | S57: 11121 | T57: 5561 | U57: 741 | V57: 556 | W57: 0 | X57: 0 | Y57: 556 | Z57: 556 | AA57: 0 | AB57: 0 | AC57: 0 | AD57: 0 | AE57: 0 | AF57: 0 | AG57: 0 | AH57: 0 | AI57: 0 | AJ57: ='Row data'!$S57+'Row data'!$T57+'Row data'!$U57+'Row data'!$W57+'Row data'!$X57+'Row data'!$Y57+'Row data'!$Z57+'Row data'!$AA57+'Row data'!$AB57+'Row data'!$AD57-'Row data'!$AC57-'Row data'!$AE57-'Row data'!$AF57-'Row data'!$AG57-'Row data'!$AH57-'Row data'!$AI57 -> 18535 | AK57: 18535 | AL57: 0
A58: 57 | B58: ABC Textile Ltd. | C58: 5456525 | D58: Naim | E58: Utility & Maintenance | F58: Electrical | G58: Assistant Electrician | H58: 703204000030948 | I58: 43771 | L58: 31211 | M58: =IF('Row data'!$J58="",DATEDIF('Row data'!$L58,TODAY(),"y"),"0") -> 41 | N58: M | O58: N | P58: Staff | Q58: 21309 | R58: 21309 | S58: 12786 | T58: 6393 | U58: 852 | V58: 639 | W58: 0 | X58: 0 | Y58: 639 | Z58: 639 | AA58: 0 | AB58: 0 | AC58: 0 | AD58: 0 | AE58: 0 | AF58: 0 | AG58: 0 | AH58: 0 | AI58: 0 | AJ58: ='Row data'!$S58+'Row data'!$T58+'Row data'!$U58+'Row data'!$W58+'Row data'!$X58+'Row data'!$Y58+'Row data'!$Z58+'Row data'!$AA58+'Row data'!$AB58+'Row data'!$AD58-'Row data'!$AC58-'Row data'!$AE58-'Row data'!$AF58-'Row data'!$AG58-'Row data'!$AH58-'Row data'!$AI58 -> 21309 | AK58: 21309 | AL58: 0
A59: 58 | B59: ABC Textile Ltd. | C59: 8766545 | D59: Nasir | E59: Utility & Maintenance | F59: Electrical | G59: Sr. Shift Engineer | H59: 703204000031102 | I59: 42594 | L59: 34554 | M59: =IF('Row data'!$J59="",DATEDIF('Row data'!$L59,TODAY(),"y"),"0") -> 32 | N59: M | O59: N | P59: Staff | Q59: 43056 | R59: 43056 | S59: 25833 | T59: 12917 | U59: 1722 | V59: 1292 | W59: 0 | X59: 0 | Y59: 1292 | Z59: 1292 | AA59: 0 | AB59: 0 | AC59: 0 | AD59: 0 | AE59: 0 | AF59: 0 | AG59: 0 | AH59: 0 | AI59: 0 | AJ59: ='Row data'!$S59+'Row data'!$T59+'Row data'!$U59+'Row data'!$W59+'Row data'!$X59+'Row data'!$Y59+'Row data'!$Z59+'Row data'!$AA59+'Row data'!$AB59+'Row data'!$AD59-'Row data'!$AC59-'Row data'!$AE59-'Row data'!$AF59-'Row data'!$AG59-'Row data'!$AH59-'Row data'!$AI59 -> 43056 | AK59: 43056 | AL59: 0
A60: 59 | B60: ABC Textile Ltd. | C60: 9983256 | D60: Nazmul | E60: Utility & Maintenance | F60: Electrical | G60: Assistant Electrician | H60: 703204000030471 | I60: 42921 | L60: 34700 | M60: =IF('Row data'!$J60="",DATEDIF('Row data'!$L60,TODAY(),"y"),"0") -> 31 | N60: M | O60: N | P60: Staff | Q60: 21256 | R60: 16256 | S60: 12753 | T60: 6377 | U60: 850 | V60: 638 | W60: 0 | X60: 0 | Y60: 638 | Z60: 638 | AA60: 0 | AB60: 0 | AC60: -5000 | AD60: 0 | AE60: 0 | AF60: 0 | AG60: 0 | AH60: 0 | AI60: 0 | AJ60: ='Row data'!$S60+'Row data'!$T60+'Row data'!$U60+'Row data'!$W60+'Row data'!$X60+'Row data'!$Y60+'Row data'!$Z60+'Row data'!$AA60+'Row data'!$AB60+'Row data'!$AD60-'Row data'!$AC60-'Row data'!$AE60-'Row data'!$AF60-'Row data'!$AG60-'Row data'!$AH60-'Row data'!$AI60 -> 26256 | AK60: 16256 | AL60: 0
A61: 60 | B61: ABC Textile Ltd. | C61: 7769442 | D61: Niaz | E61: Utility & Maintenance | F61: Electrical | G61: Electrician | H61: 7863241000346900 | I61: 43374 | L61: 35617 | M61: =IF('Row data'!$J61="",DATEDIF('Row data'!$L61,TODAY(),"y"),"0") -> 29 | N61: M | O61: N | P61: Staff | Q61: 30259 | R61: 30259 | S61: 18155 | T61: 9078 | U61: 1210 | V61: 908 | W61: 0 | X61: 0 | Y61: 908 | Z61: 908 | AA61: 0 | AB61: 0 | AC61: 0 | AD61: 0 | AE61: 0 | AF61: 0 | AG61: 0 | AH61: 0 | AI61: 0 | AJ61: ='Row data'!$S61+'Row data'!$T61+'Row data'!$U61+'Row data'!$W61+'Row data'!$X61+'Row data'!$Y61+'Row data'!$Z61+'Row data'!$AA61+'Row data'!$AB61+'Row data'!$AD61-'Row data'!$AC61-'Row data'!$AE61-'Row data'!$AF61-'Row data'!$AG61-'Row data'!$AH61-'Row data'!$AI61 -> 30259 | AK61: 30259 | AL61: 0
A62: 61 | B62: ABC Textile Ltd. | C62: 5377015 | D62: Nurul | E62: Utility & Maintenance | F62: Electrical | G62: Maintenance Officer | H62: 9993201000374800 | I62: 44593 | L62: 30056 | M62: =IF('Row data'!$J62="",DATEDIF('Row data'!$L62,TODAY(),"y"),"0") -> 44 | N62: M | O62: N | P62: Staff | Q62: 41966 | R62: 41966 | S62: 25179 | T62: 12590 | U62: 1679 | V62: 1259 | W62: 0 | X62: 0 | Y62: 1259 | Z62: 1259 | AA62: 0 | AB62: 0 | AC62: 0 | AD62: 0 | AE62: 0 | AF62: 0 | AG62: 0 | AH62: 0 | AI62: 0 | AJ62: ='Row data'!$S62+'Row data'!$T62+'Row data'!$U62+'Row data'!$W62+'Row data'!$X62+'Row data'!$Y62+'Row data'!$Z62+'Row data'!$AA62+'Row data'!$AB62+'Row data'!$AD62-'Row data'!$AC62-'Row data'!$AE62-'Row data'!$AF62-'Row data'!$AG62-'Row data'!$AH62-'Row data'!$AI62 -> 41966 | AK62: 41966 | AL62: 0
A63: 62 | B63: ABC Textile Ltd. | C63: 7321525 | D63: Parvez | E63: Utility & Maintenance | F63: Electrical | G63: Asst. Manager | H63: 9993201000364090 | I63: 44550 | L63: 33147 | M63: =IF('Row data'!$J63="",DATEDIF('Row data'!$L63,TODAY(),"y"),"0") -> 35 | N63: M | O63: N | P63: Staff | Q63: 51230 | R63: 51230 | S63: 30738 | T63: 15369 | U63: 2049 | V63: 1537 | W63: 0 | X63: 0 | Y63: 1537 | Z63: 1537 | AA63: 0 | AB63: 0 | AC63: 0 | AD63: 0 | AE63: 0 | AF63: 0 | AG63: 0 | AH63: 556 | AI63: 0 | AJ63: ='Row data'!$S63+'Row data'!$T63+'Row data'!$U63+'Row data'!$W63+'Row data'!$X63+'Row data'!$Y63+'Row data'!$Z63+'Row data'!$AA63+'Row data'!$AB63+'Row data'!$AD63-'Row data'!$AC63-'Row data'!$AE63-'Row data'!$AF63-'Row data'!$AG63-'Row data'!$AH63-'Row data'!$AI63 -> 50674 | AK63: 50674 | AL63: 0
A64: 63 | B64: ABC Textile Ltd. | C64: 9785895 | D64: Pritom | E64: Utility & Maintenance | F64: Mechanical | G64: Head Fitter | H64: 9993201000366020 | I64: 44515 | L64: 34403 | M64: =IF('Row data'!$J64="",DATEDIF('Row data'!$L64,TODAY(),"y"),"0") -> 32 | N64: M | O64: N | P64: Staff | Q64: 27576 | R64: 27576 | S64: 16546 | T64: 8273 | U64: 1103 | V64: 827 | W64: 0 | X64: 0 | Y64: 827 | Z64: 827 | AA64: 0 | AB64: 0 | AC64: 0 | AD64: 0 | AE64: 0 | AF64: 0 | AG64: 0 | AH64: 0 | AI64: 0 | AJ64: ='Row data'!$S64+'Row data'!$T64+'Row data'!$U64+'Row data'!$W64+'Row data'!$X64+'Row data'!$Y64+'Row data'!$Z64+'Row data'!$AA64+'Row data'!$AB64+'Row data'!$AD64-'Row data'!$AC64-'Row data'!$AE64-'Row data'!$AF64-'Row data'!$AG64-'Row data'!$AH64-'Row data'!$AI64 -> 27576 | AK64: 27576 | AL64: 0
A65: 64 | B65: ABC Textile Ltd. | C65: 8952953 | D65: Rahat | E65: Utility & Maintenance | F65: Mechanical | G65: Assistant Fitter Man | H65: 703204000030999 | I65: 44844 | L65: 33113 | M65: =IF('Row data'!$J65="",DATEDIF('Row data'!$L65,TODAY(),"y"),"0") -> 36 | N65: M | O65: N | P65: Staff | Q65: 16126 | R65: 16126 | S65: 9675 | T65: 4838 | U65: 645 | V65: 484 | W65: 0 | X65: 0 | Y65: 484 | Z65: 484 | AA65: 0 | AB65: 0 | AC65: 0 | AD65: 0 | AE65: 0 | AF65: 0 | AG65: 0 | AH65: 0 | AI65: 0 | AJ65: ='Row data'!$S65+'Row data'!$T65+'Row data'!$U65+'Row data'!$W65+'Row data'!$X65+'Row data'!$Y65+'Row data'!$Z65+'Row data'!$AA65+'Row data'!$AB65+'Row data'!$AD65-'Row data'!$AC65-'Row data'!$AE65-'Row data'!$AF65-'Row data'!$AG65-'Row data'!$AH65-'Row data'!$AI65 -> 16126 | AK65: 16126 | AL65: 0
A66: 65 | B66: ABC Textile Ltd. | C66: 8351522 | D66: Rakib | E66: Utility & Maintenance | F66: Mechanical | G66: Assistant Fitter Man | H66: 9993204000003100 | I66: 45172 | L66: 34700 | M66: =IF('Row data'!$J66="",DATEDIF('Row data'!$L66,TODAY(),"y"),"0") -> 31 | N66: M | O66: N | P66: Staff | Q66: 18530 | R66: 18530 | S66: 11118 | T66: 5559 | U66: 741 | V66: 556 | W66: 0 | X66: 0 | Y66: 556 | Z66: 556 | AA66: 0 | AB66: 0 | AC66: 0 | AD66: 0 | AE66: 0 | AF66: 0 | AG66: 0 | AH66: 0 | AI66: 0 | AJ66: ='Row data'!$S66+'Row data'!$T66+'Row data'!$U66+'Row data'!$W66+'Row data'!$X66+'Row data'!$Y66+'Row data'!$Z66+'Row data'!$AA66+'Row data'!$AB66+'Row data'!$AD66-'Row data'!$AC66-'Row data'!$AE66-'Row data'!$AF66-'Row data'!$AG66-'Row data'!$AH66-'Row data'!$AI66 -> 18530 | AK66: 18530 | AL66: 0
A67: 66 | B67: ABC Textile Ltd. | C67: 5603019 | D67: Rashid | E67: Utility & Maintenance | F67: Mechanical | G67: Mechanical Fitter Man | H67: 783204000012196 | I67: 40372 | L67: 29008 | M67: =IF('Row data'!$J67="",DATEDIF('Row data'!$L67,TODAY(),"y"),"0") -> 47 | N67: M | O67: N | P67: Staff | Q67: 35533 | R67: 35533 | S67: 21320 | T67: 10660 | U67: 1421 | V67: 1066 | W67: 0 | X67: 0 | Y67: 1066 | Z67: 1066 | AA67: 0 | AB67: 0 | AC67: 0 | AD67: 0 | AE67: 0 | AF67: 0 | AG67: 5000 | AH67: 0 | AI67: 0 | AJ67: ='Row data'!$S67+'Row data'!$T67+'Row data'!$U67+'Row data'!$W67+'Row data'!$X67+'Row data'!$Y67+'Row data'!$Z67+'Row data'!$AA67+'Row data'!$AB67+'Row data'!$AD67-'Row data'!$AC67-'Row data'!$AE67-'Row data'!$AF67-'Row data'!$AG67-'Row data'!$AH67-'Row data'!$AI67 -> 30533 | AK67: 30533 | AL67: 0
A68: 67 | B68: ABC Textile Ltd. | C68: 8751987 | D68: Rayhan | E68: Utility & Maintenance | F68: Mechanical | G68: Sr. Shift Engineer | H68: 703204000031055 | I68: 42957 | L68: 34101 | M68: =IF('Row data'!$J68="",DATEDIF('Row data'!$L68,TODAY(),"y"),"0") -> 33 | N68: M | O68: N | P68: Staff | Q68: 37060 | R68: 37060 | S68: 22236 | T68: 11118 | U68: 1482 | V68: 1112 | W68: 0 | X68: 0 | Y68: 1112 | Z68: 1112 | AA68: 0 | AB68: 0 | AC68: 0 | AD68: 0 | AE68: 0 | AF68: 0 | AG68: 0 | AH68: 0 | AI68: 0 | AJ68: ='Row data'!$S68+'Row data'!$T68+'Row data'!$U68+'Row data'!$W68+'Row data'!$X68+'Row data'!$Y68+'Row data'!$Z68+'Row data'!$AA68+'Row data'!$AB68+'Row data'!$AD68-'Row data'!$AC68-'Row data'!$AE68-'Row data'!$AF68-'Row data'!$AG68-'Row data'!$AH68-'Row data'!$AI68 -> 37060 | AK68: 37060 | AL68: 0
A69: 68 | B69: ABC Textile Ltd. | C69: 9143499 | D69: Reaz | E69: Utility & Maintenance | F69: Mechanical | G69: Assistant Fitter Man | H69: 703204000030482 | I69: 43739 | L69: 35710 | M69: =IF('Row data'!$J69="",DATEDIF('Row data'!$L69,TODAY(),"y"),"0") -> 28 | N69: M | O69: N | P69: Staff | Q69: 21256 | R69: 21256 | S69: 12753 | T69: 6377 | U69: 850 | V69: 638 | W69: 0 | X69: 0 | Y69: 638 | Z69: 638 | AA69: 0 | AB69: 0 | AC69: 0 | AD69: 0 | AE69: 0 | AF69: 0 | AG69: 0 | AH69: 0 | AI69: 0 | AJ69: ='Row data'!$S69+'Row data'!$T69+'Row data'!$U69+'Row data'!$W69+'Row data'!$X69+'Row data'!$Y69+'Row data'!$Z69+'Row data'!$AA69+'Row data'!$AB69+'Row data'!$AD69-'Row data'!$AC69-'Row data'!$AE69-'Row data'!$AF69-'Row data'!$AG69-'Row data'!$AH69-'Row data'!$AI69 -> 21256 | AK69: 21256 | AL69: 0
A70: 69 | B70: ABC J (Bangladesh) Ltd. | C70: 5484198 | D70: Ridwan | E70: Accounts | F70: Accounts | G70: Senior Executive | H70: 9993204000003410 | I70: 41974 | J70: 45291 | K70: =YEAR('Row data'!$J70) -> 2023 | L70: 32508 | M70: =IF('Row data'!$J70="",DATEDIF('Row data'!$L70,TODAY(),"y"),"0") -> 0 | N70: M | O70: N | P70: Staff | Q70: 46870 | R70: 46870 | S70: 28122 | T70: 14061 | U70: 1875 | V70: 1406 | W70: 0 | X70: 0 | Y70: 1406 | Z70: 1406 | AA70: 0 | AB70: 0 | AC70: 0 | AD70: 0 | AE70: 0 | AF70: 0 | AG70: 0 | AH70: 0 | AI70: 0 | AJ70: ='Row data'!$S70+'Row data'!$T70+'Row data'!$U70+'Row data'!$W70+'Row data'!$X70+'Row data'!$Y70+'Row data'!$Z70+'Row data'!$AA70+'Row data'!$AB70+'Row data'!$AD70-'Row data'!$AC70-'Row data'!$AE70-'Row data'!$AF70-'Row data'!$AG70-'Row data'!$AH70-'Row data'!$AI70 -> 46870 | AK70: 46870 | AL70: 0
A71: 70 | B71: ABC J (Bangladesh) Ltd. | C71: 7798029 | D71: Rifat | E71: Accounts | F71: Accounts | G71: Assistant Manager | H71: 703204000030799 | I71: 43253 | L71: 30950 | M71: =IF('Row data'!$J71="",DATEDIF('Row data'!$L71,TODAY(),"y"),"0") -> 41 | N71: M | O71: N | P71: Staff | Q71: 48941 | R71: 48941 | S71: 29365 | T71: 14682 | U71: 1958 | V71: 1468 | W71: 0 | X71: 0 | Y71: 1468 | Z71: 1468 | AA71: 0 | AB71: 0 | AC71: 0 | AD71: 0 | AE71: 0 | AF71: 0 | AG71: 0 | AH71: 300 | AI71: 0 | AJ71: ='Row data'!$S71+'Row data'!$T71+'Row data'!$U71+'Row data'!$W71+'Row data'!$X71+'Row data'!$Y71+'Row data'!$Z71+'Row data'!$AA71+'Row data'!$AB71+'Row data'!$AD71-'Row data'!$AC71-'Row data'!$AE71-'Row data'!$AF71-'Row data'!$AG71-'Row data'!$AH71-'Row data'!$AI71 -> 48641 | AK71: 48641 | AL71: 0
A72: 71 | B72: ABC J (Bangladesh) Ltd. | C72: 5514537 | D72: Ripon | E72: Admin | F72: Canteen | G72: Canteen Boy | H72: 703204000030458 | I72: 41699 | L72: 34700 | M72: =IF('Row data'!$J72="",DATEDIF('Row data'!$L72,TODAY(),"y"),"0") -> 31 | N72: M | O72: N | P72: Staff | Q72: 17991 | R72: 12991 | S72: 10794 | T72: 5397 | U72: 720 | V72: 540 | W72: 0 | X72: 0 | Y72: 540 | Z72: 540 | AA72: 0 | AB72: 0 | AC72: -5000 | AD72: 0 | AE72: 0 | AF72: 0 | AG72: 0 | AH72: 0 | AI72: 0 | AJ72: ='Row data'!$S72+'Row data'!$T72+'Row data'!$U72+'Row data'!$W72+'Row data'!$X72+'Row data'!$Y72+'Row data'!$Z72+'Row data'!$AA72+'Row data'!$AB72+'Row data'!$AD72-'Row data'!$AC72-'Row data'!$AE72-'Row data'!$AF72-'Row data'!$AG72-'Row data'!$AH72-'Row data'!$AI72 -> 22991 | AK72: 12991 | AL72: 0
A73: 72 | B73: ABC J (Bangladesh) Ltd. | C73: 7731098 | D73: Rizvi | E73: Admin | F73: Child Care | G73: Governess | H73: 9993204000003210 | I73: 42753 | L73: 33984 | M73: =IF('Row data'!$J73="",DATEDIF('Row data'!$L73,TODAY(),"y"),"0") -> 33 | N73: F | O73: N | P73: Staff | Q73: 17767 | R73: 13325 | S73: 10660 | T73: 5330 | U73: 711 | V73: 533 | W73: 0 | X73: 0 | Y73: 533 | Z73: 533 | AA73: 0 | AB73: 0 | AC73: -4442 | AD73: 0 | AE73: 0 | AF73: 0 | AG73: 0 | AH73: 0 | AI73: 0 | AJ73: ='Row data'!$S73+'Row data'!$T73+'Row data'!$U73+'Row data'!$W73+'Row data'!$X73+'Row data'!$Y73+'Row data'!$Z73+'Row data'!$AA73+'Row data'!$AB73+'Row data'!$AD73-'Row data'!$AC73-'Row data'!$AE73-'Row data'!$AF73-'Row data'!$AG73-'Row data'!$AH73-'Row data'!$AI73 -> 22209 | AK73: 13325 | AL73: 0
A74: 73 | B74: ABC J (Bangladesh) Ltd. | C74: 9454142 | D74: Rubel | E74: Admin | F74: Factory Affairs | G74: General Manager | H74: 703204000030904 | I74: 41426 | J74: 44927 | K74: =YEAR('Row data'!$J74) -> 2023 | L74: 24625 | M74: =IF('Row data'!$J74="",DATEDIF('Row data'!$L74,TODAY(),"y"),"0") -> 0 | N74: M | O74: N | P74: Staff | Q74: 185000 | R74: 185000 | S74: 111000 | T74: 55500 | U74: 7400 | V74: 5550 | W74: 0 | X74: 0 | Y74: 5550 | Z74: 5550 | AA74: 0 | AB74: 0 | AC74: 0 | AD74: 0 | AE74: 0 | AF74: 0 | AG74: 0 | AH74: 16000 | AI74: 0 | AJ74: ='Row data'!$S74+'Row data'!$T74+'Row data'!$U74+'Row data'!$W74+'Row data'!$X74+'Row data'!$Y74+'Row data'!$Z74+'Row data'!$AA74+'Row data'!$AB74+'Row data'!$AD74-'Row data'!$AC74-'Row data'!$AE74-'Row data'!$AF74-'Row data'!$AG74-'Row data'!$AH74-'Row data'!$AI74 -> 169000 | AK74: 169000 | AL74: 0
A75: 74 | B75: ABC J (Bangladesh) Ltd. | C75: 6334717 | D75: Rumman | E75: Admin | F75: Medical | G75: Nurse | H75: 703204000029461 | I75: 42679 | L75: 34773 | M75: =IF('Row data'!$J75="",DATEDIF('Row data'!$L75,TODAY(),"y"),"0") -> 31 | N75: F | O75: N | P75: Staff | Q75: 32179 | R75: 32179 | S75: 19308 | T75: 9654 | U75: 1287 | V75: 965 | W75: 0 | X75: 0 | Y75: 965 | Z75: 965 | AA75: 0 | AB75: 0 | AC75: 0 | AD75: 0 | AE75: 0 | AF75: 0 | AG75: 0 | AH75: 0 | AI75: 0 | AJ75: ='Row data'!$S75+'Row data'!$T75+'Row data'!$U75+'Row data'!$W75+'Row data'!$X75+'Row data'!$Y75+'Row data'!$Z75+'Row data'!$AA75+'Row data'!$AB75+'Row data'!$AD75-'Row data'!$AC75-'Row data'!$AE75-'Row data'!$AF75-'Row data'!$AG75-'Row data'!$AH75-'Row data'!$AI75 -> 32179 | AK75: 32179 | AL75: 0
A76: 75 | B76: ABC J (Bangladesh) Ltd. | C76: 9274196 | D76: Saad | E76: Admin | F76: Security | G76: Security Trainee Supervisor | H76: 703204000029528 | I76: 41415 | L76: 27525 | M76: =IF('Row data'!$J76="",DATEDIF('Row data'!$L76,TODAY(),"y"),"0") -> 51 | N76: M | O76: N | P76: Staff | Q76: 24198 | R76: 24198 | S76: 14519 | T76: 7259 | U76: 968 | V76: 726 | W76: 0 | X76: 0 | Y76: 726 | Z76: 726 | AA76: 0 | AB76: 0 | AC76: 0 | AD76: 0 | AE76: 0 | AF76: 0 | AG76: 0 | AH76: 0 | AI76: 0 | AJ76: ='Row data'!$S76+'Row data'!$T76+'Row data'!$U76+'Row data'!$W76+'Row data'!$X76+'Row data'!$Y76+'Row data'!$Z76+'Row data'!$AA76+'Row data'!$AB76+'Row data'!$AD76-'Row data'!$AC76-'Row data'!$AE76-'Row data'!$AF76-'Row data'!$AG76-'Row data'!$AH76-'Row data'!$AI76 -> 24198 | AK76: 24198 | AL76: 0
A77: 76 | B77: ABC J (Bangladesh) Ltd. | C77: 5804642 | D77: Sabbir | E77: Admin | F77: Security | G77: Security Guard | H77: 703204000029348 | I77: 40360 | J77: 44927 | K77: =YEAR('Row data'!$J77) -> 2023 | L77: 24901 | M77: =IF('Row data'!$J77="",DATEDIF('Row data'!$L77,TODAY(),"y"),"0") -> 0 | N77: M | O77: N | P77: Staff | Q77: 23226 | R77: 23226 | S77: 13935 | T77: 6968 | U77: 929 | V77: 697 | W77: 0 | X77: 0 | Y77: 697 | Z77: 697 | AA77: 0 | AB77: 0 | AC77: 0 | AD77: 0 | AE77: 0 | AF77: 0 | AG77: 0 | AH77: 0 | AI77: 0 | AJ77: ='Row data'!$S77+'Row data'!$T77+'Row data'!$U77+'Row data'!$W77+'Row data'!$X77+'Row data'!$Y77+'Row data'!$Z77+'Row data'!$AA77+'Row data'!$AB77+'Row data'!$AD77-'Row data'!$AC77-'Row data'!$AE77-'Row data'!$AF77-'Row data'!$AG77-'Row data'!$AH77-'Row data'!$AI77 -> 23226 | AK77: 23226 | AL77: 0
A78: 77 | B78: ABC J (Bangladesh) Ltd. | C78: 5345011 | D78: Sadman | E78: Admin | F78: Security | G78: Security Guard | H78: 703204000029417 | I78: 40550 | J78: 44927 | K78: =YEAR('Row data'!$J78) -> 2023 | L78: 24237 | M78: =IF('Row data'!$J78="",DATEDIF('Row data'!$L78,TODAY(),"y"),"0") -> 0 | N78: M | O78: N | P78: Staff | Q78: 24184 | R78: 24184 | S78: 14510 | T78: 7255 | U78: 967 | V78: 726 | W78: 0 | X78: 0 | Y78: 726 | Z78: 726 | AA78: 0 | AB78: 0 | AC78: 0 | AD78: 0 | AE78: 0 | AF78: 0 | AG78: 0 | AH78: 0 | AI78: 0 | AJ78: ='Row data'!$S78+'Row data'!$T78+'Row data'!$U78+'Row data'!$W78+'Row data'!$X78+'Row data'!$Y78+'Row data'!$Z78+'Row data'!$AA78+'Row data'!$AB78+'Row data'!$AD78-'Row data'!$AC78-'Row data'!$AE78-'Row data'!$AF78-'Row data'!$AG78-'Row data'!$AH78-'Row data'!$AI78 -> 24184 | AK78: 24184 | AL78: 0
A79: 78 | B79: ABC J (Bangladesh) Ltd. | C79: 9110823 | D79: Saeed | E79: Admin | F79: Security | G79: Security In charge | H79: 9993204000003500 | I79: 45301 | J79: 44927 | K79: =YEAR('Row data'!$J79) -> 2023 | L79: 29285 | M79: =IF('Row data'!$J79="",DATEDIF('Row data'!$L79,TODAY(),"y"),"0") -> 0 | N79: M | O79: N | P79: Staff | Q79: 25000 | R79: 25000 | S79: 14500 | T79: 7250 | U79: 1450 | V79: 1800 | W79: 0 | X79: 0 | Y79: 0 | Z79: 1800 | AA79: 0 | AB79: 0 | AC79: 0 | AD79: 0 | AE79: 0 | AF79: 0 | AG79: 0 | AH79: 0 | AI79: 0 | AJ79: ='Row data'!$S79+'Row data'!$T79+'Row data'!$U79+'Row data'!$W79+'Row data'!$X79+'Row data'!$Y79+'Row data'!$Z79+'Row data'!$AA79+'Row data'!$AB79+'Row data'!$AD79-'Row data'!$AC79-'Row data'!$AE79-'Row data'!$AF79-'Row data'!$AG79-'Row data'!$AH79-'Row data'!$AI79 -> 25000 | AK79: 25000 | AL79: 0
A80: 79 | B80: ABC J (Bangladesh) Ltd. | C80: 6416473 | D80: Sagor | E80: Admin | F80: Security | G80: Lady Checker | H80: 703204000029392 | I80: 44593 | L80: 33770 | M80: =IF('Row data'!$J80="",DATEDIF('Row data'!$L80,TODAY(),"y"),"0") -> 34 | N80: F | O80: N | P80: Staff | Q80: 16153 | R80: 8365 | S80: 9691 | T80: 4846 | U80: 646 | V80: 485 | W80: 0 | X80: 0 | Y80: 485 | Z80: 485 | AA80: 0 | AB80: 0 | AC80: -7788 | AD80: 0 | AE80: 0 | AF80: 0 | AG80: 500 | AH80: 0 | AI80: 0 | AJ80: ='Row data'!$S80+'Row data'!$T80+'Row data'!$U80+'Row data'!$W80+'Row data'!$X80+'Row data'!$Y80+'Row data'!$Z80+'Row data'!$AA80+'Row data'!$AB80+'Row data'!$AD80-'Row data'!$AC80-'Row data'!$AE80-'Row data'!$AF80-'Row data'!$AG80-'Row data'!$AH80-'Row data'!$AI80 -> 23441 | AK80: 7865 | AL80: 0
A81: 80 | B81: ABC J (Bangladesh) Ltd. | C81: 9427349 | D81: Sajib | E81: Admin | F81: Supports | G81: Lift Operator | H81: 703204000029541 | I81: 44632 | L81: 37914 | M81: =IF('Row data'!$J81="",DATEDIF('Row data'!$L81,TODAY(),"y"),"0") -> 22 | N81: M | O81: N | P81: Staff | Q81: 18608 | R81: 18608 | S81: 11165 | T81: 5583 | U81: 744 | V81: 558 | W81: 0 | X81: 0 | Y81: 558 | Z81: 558 | AA81: 0 | AB81: 0 | AC81: 0 | AD81: 0 | AE81: 0 | AF81: 0 | AG81: 0 | AH81: 0 | AI81: 0 | AJ81: ='Row data'!$S81+'Row data'!$T81+'Row data'!$U81+'Row data'!$W81+'Row data'!$X81+'Row data'!$Y81+'Row data'!$Z81+'Row data'!$AA81+'Row data'!$AB81+'Row data'!$AD81-'Row data'!$AC81-'Row data'!$AE81-'Row data'!$AF81-'Row data'!$AG81-'Row data'!$AH81-'Row data'!$AI81 -> 18608 | AK81: 18608 | AL81: 0
A82: 81 | B82: ABC J (Bangladesh) Ltd. | C82: 7594421 | D82: Sajjad | E82: Admin | F82: Supports | G82: Loader | H82: 70320400031000 | I82: 42756 | L82: 30817 | M82: =IF('Row data'!$J82="",DATEDIF('Row data'!$L82,TODAY(),"y"),"0") -> 42 | N82: M | O82: N | P82: Staff | Q82: 16248 | R82: 16248 | S82: 9749 | T82: 4875 | U82: 650 | V82: 487 | W82: 0 | X82: 0 | Y82: 487 | Z82: 487 | AA82: 0 | AB82: 0 | AC82: 0 | AD82: 0 | AE82: 0 | AF82: 0 | AG82: 0 | AH82: 0 | AI82: 0 | AJ82: ='Row data'!$S82+'Row data'!$T82+'Row data'!$U82+'Row data'!$W82+'Row data'!$X82+'Row data'!$Y82+'Row data'!$Z82+'Row data'!$AA82+'Row data'!$AB82+'Row data'!$AD82-'Row data'!$AC82-'Row data'!$AE82-'Row data'!$AF82-'Row data'!$AG82-'Row data'!$AH82-'Row data'!$AI82 -> 16248 | AK82: 16248 | AL82: 0
A83: 82 | B83: ABC J (Bangladesh) Ltd. | C83: 5109286 | D83: Saleh | E83: Admin | F83: Vehicle Management | G83: Driver | H83: 9993204000004930 | I83: 45566 | J83: 44927 | K83: =YEAR('Row data'!$J83) -> 2023 | L83: 27636 | M83: =IF('Row data'!$J83="",DATEDIF('Row data'!$L83,TODAY(),"y"),"0") -> 0 | N83: M | O83: N | P83: Staff | Q83: 20000 | R83: 20000 | S83: 11600 | T83: 5800 | U83: 1160 | V83: 1440 | W83: 0 | X83: 0 | Y83: 0 | Z83: 1440 | AA83: 0 | AB83: 0 | AC83: 0 | AD83: 0 | AE83: 0 | AF83: 0 | AG83: 0 | AH83: 0 | AI83: 0 | AJ83: ='Row data'!$S83+'Row data'!$T83+'Row data'!$U83+'Row data'!$W83+'Row data'!$X83+'Row data'!$Y83+'Row data'!$Z83+'Row data'!$AA83+'Row data'!$AB83+'Row data'!$AD83-'Row data'!$AC83-'Row data'!$AE83-'Row data'!$AF83-'Row data'!$AG83-'Row data'!$AH83-'Row data'!$AI83 -> 20000 | AK83: 20000 | AL83: 0
A84: 83 | B84: ABC J (Bangladesh) Ltd. | C84: 6379063 | D84: Salim | E84: Delivery | F84: Delivery | G84: Asst. Manager Operation (Bottle & Logistic Support | H84: 703204000029337 | I84: 35582 | L84: 27103 | M84: =IF('Row data'!$J84="",DATEDIF('Row data'!$L84,TODAY(),"y"),"0") -> 52 | N84: M | O84: N | P84: Staff | Q84: 73087 | R84: 73087 | S84: 43852 | T84: 21926 | U84: 2923 | V84: 2193 | W84: 0 | X84: 0 | Y84: 2193 | Z84: 2193 | AA84: 0 | AB84: 0 | AC84: 0 | AD84: 0 | AE84: 0 | AF84: 0 | AG84: 0 | AH84: 1000 | AI84: 0 | AJ84: ='Row data'!$S84+'Row data'!$T84+'Row data'!$U84+'Row data'!$W84+'Row data'!$X84+'Row data'!$Y84+'Row data'!$Z84+'Row data'!$AA84+'Row data'!$AB84+'Row data'!$AD84-'Row data'!$AC84-'Row data'!$AE84-'Row data'!$AF84-'Row data'!$AG84-'Row data'!$AH84-'Row data'!$AI84 -> 72087 | AK84: 72087 | AL84: 0
A85: 84 | B85: ABC J (Bangladesh) Ltd. | C85: 6852588 | D85: Samir | E85: Delivery | F85: Delivery | G85: Delivery Executive | H85: 703204000030788 | I85: 42522 | L85: 31318 | M85: =IF('Row data'!$J85="",DATEDIF('Row data'!$L85,TODAY(),"y"),"0") -> 40 | N85: M | O85: N | P85: Staff | Q85: 30476 | R85: 30476 | S85: 18286 | T85: 9143 | U85: 1219 | V85: 914 | W85: 0 | X85: 0 | Y85: 914 | Z85: 914 | AA85: 0 | AB85: 0 | AC85: 0 | AD85: 0 | AE85: 0 | AF85: 0 | AG85: 0 | AH85: 0 | AI85: 0 | AJ85: ='Row data'!$S85+'Row data'!$T85+'Row data'!$U85+'Row data'!$W85+'Row data'!$X85+'Row data'!$Y85+'Row data'!$Z85+'Row data'!$AA85+'Row data'!$AB85+'Row data'!$AD85-'Row data'!$AC85-'Row data'!$AE85-'Row data'!$AF85-'Row data'!$AG85-'Row data'!$AH85-'Row data'!$AI85 -> 30476 | AK85: 30476 | AL85: 0
A86: 85 | B86: ABC J (Bangladesh) Ltd. | C86: 6472986 | D86: Sarwar | E86: HR & Compliance | F86: Administration | G86: Assistant Manager | H86: 7863241000485150 | I86: 40338 | L86: 31048 | M86: =IF('Row data'!$J86="",DATEDIF('Row data'!$L86,TODAY(),"y"),"0") -> 41 | N86: M | O86: N | P86: Staff | Q86: 45235 | R86: 45235 | S86: 27141 | T86: 13571 | U86: 1809 | V86: 1357 | W86: 0 | X86: 0 | Y86: 1357 | Z86: 1357 | AA86: 0 | AB86: 0 | AC86: 0 | AD86: 0 | AE86: 0 | AF86: 0 | AG86: 0 | AH86: 0 | AI86: 0 | AJ86: ='Row data'!$S86+'Row data'!$T86+'Row data'!$U86+'Row data'!$W86+'Row data'!$X86+'Row data'!$Y86+'Row data'!$Z86+'Row data'!$AA86+'Row data'!$AB86+'Row data'!$AD86-'Row data'!$AC86-'Row data'!$AE86-'Row data'!$AF86-'Row data'!$AG86-'Row data'!$AH86-'Row data'!$AI86 -> 45235 | AK86: 45235 | AL86: 0
A87: 86 | B87: ABC J (Bangladesh) Ltd. | C87: 9810044 | D87: Shafayet | E87: HR & Compliance | F87: HR | G87: Senior Executive | H87: 7863241000488270 | I87: 42125 | L87: 32538 | M87: =IF('Row data'!$J87="",DATEDIF('Row data'!$L87,TODAY(),"y"),"0") -> 37 | N87: M | O87: N | P87: Staff | Q87: 36515 | R87: 31515 | S87: 21909 | T87: 10955 | U87: 1461 | V87: 1095 | W87: 0 | X87: 0 | Y87: 1095 | Z87: 1095 | AA87: 0 | AB87: 0 | AC87: -5000 | AD87: 0 | AE87: 0 | AF87: 0 | AG87: 4000 | AH87: 0 | AI87: 0 | AJ87: ='Row data'!$S87+'Row data'!$T87+'Row data'!$U87+'Row data'!$W87+'Row data'!$X87+'Row data'!$Y87+'Row data'!$Z87+'Row data'!$AA87+'Row data'!$AB87+'Row data'!$AD87-'Row data'!$AC87-'Row data'!$AE87-'Row data'!$AF87-'Row data'!$AG87-'Row data'!$AH87-'Row data'!$AI87 -> 37515 | AK87: 27515 | AL87: 0
A88: 87 | B88: ABC J (Bangladesh) Ltd. | C88: 8984117 | D88: Shahadat | E88: IT | F88: IT | G88: Senior Executive | H88: 1063204000022580 | I88: 42165 | J88: 45083 | K88: =YEAR('Row data'!$J88) -> 2023 | L88: 33761 | M88: =IF('Row data'!$J88="",DATEDIF('Row data'!$L88,TODAY(),"y"),"0") -> 0 | N88: M | O88: N | P88: Staff | Q88: 50140 | R88: 50140 | S88: 30084 | T88: 15042 | U88: 2006 | V88: 1504 | W88: 0 | X88: 0 | Y88: 1504 | Z88: 1504 | AA88: 0 | AB88: 0 | AC88: 0 | AD88: 0 | AE88: 0 | AF88: 0 | AG88: 0 | AH88: 333 | AI88: 0 | AJ88: ='Row data'!$S88+'Row data'!$T88+'Row data'!$U88+'Row data'!$W88+'Row data'!$X88+'Row data'!$Y88+'Row data'!$Z88+'Row data'!$AA88+'Row data'!$AB88+'Row data'!$AD88-'Row data'!$AC88-'Row data'!$AE88-'Row data'!$AF88-'Row data'!$AG88-'Row data'!$AH88-'Row data'!$AI88 -> 49807 | AK88: 49807 | AL88: 0
A89: 88 | B89: ABC J (Bangladesh) Ltd. | C89: 6856712 | D89: Shahid | E89: Production | F89: Cutting Export | G89: Senior Supervisor | H89: 703204000029632 | I89: 39579 | L89: 29912 | M89: =IF('Row data'!$J89="",DATEDIF('Row data'!$L89,TODAY(),"y"),"0") -> 44 | N89: M | O89: N | P89: Staff | Q89: 32321 | R89: 32321 | S89: 19392 | T89: 9696 | U89: 1293 | V89: 970 | W89: 0 | X89: 0 | Y89: 970 | Z89: 970 | AA89: 0 | AB89: 0 | AC89: 0 | AD89: 0 | AE89: 0 | AF89: 0 | AG89: 0 | AH89: 0 | AI89: 0 | AJ89: ='Row data'!$S89+'Row data'!$T89+'Row data'!$U89+'Row data'!$W89+'Row data'!$X89+'Row data'!$Y89+'Row data'!$Z89+'Row data'!$AA89+'Row data'!$AB89+'Row data'!$AD89-'Row data'!$AC89-'Row data'!$AE89-'Row data'!$AF89-'Row data'!$AG89-'Row data'!$AH89-'Row data'!$AI89 -> 32321 | AK89: 32321 | AL89: 0
A90: 89 | B90: ABC J (Bangladesh) Ltd. | C90: 8588679 | D90: Shahriar | E90: Production | F90: Finishing Export | G90: Senior Supervisor | H90: 703204000030926 | I90: 39954 | L90: 33163 | M90: =IF('Row data'!$J90="",DATEDIF('Row data'!$L90,TODAY(),"y"),"0") -> 35 | N90: M | O90: N | P90: Staff | Q90: 31282 | R90: 31282 | S90: 18770 | T90: 9385 | U90: 1251 | V90: 938 | W90: 0 | X90: 0 | Y90: 938 | Z90: 938 | AA90: 0 | AB90: 0 | AC90: 0 | AD90: 0 | AE90: 0 | AF90: 0 | AG90: 0 | AH90: 0 | AI90: 0 | AJ90: ='Row data'!$S90+'Row data'!$T90+'Row data'!$U90+'Row data'!$W90+'Row data'!$X90+'Row data'!$Y90+'Row data'!$Z90+'Row data'!$AA90+'Row data'!$AB90+'Row data'!$AD90-'Row data'!$AC90-'Row data'!$AE90-'Row data'!$AF90-'Row data'!$AG90-'Row data'!$AH90-'Row data'!$AI90 -> 31282 | AK90: 31282 | AL90: 0
A91: 90 | B91: ABC J (Bangladesh) Ltd. | C91: 5120038 | D91: Shaon | E91: Production | F91: Finishing Export | G91: Senior Packingman | H91: 9993204000003110 | I91: 39142 | L91: 31853 | M91: =IF('Row data'!$J91="",DATEDIF('Row data'!$L91,TODAY(),"y"),"0") -> 39 | N91: M | O91: N | P91: Staff | Q91: 20618 | R91: 20618 | S91: 12370 | T91: 6185 | U91: 825 | V91: 619 | W91: 0 | X91: 0 | Y91: 619 | Z91: 619 | AA91: 0 | AB91: 0 | AC91: 0 | AD91: 0 | AE91: 0 | AF91: 0 | AG91: 0 | AH91: 0 | AI91: 0 | AJ91: ='Row data'!$S91+'Row data'!$T91+'Row data'!$U91+'Row data'!$W91+'Row data'!$X91+'Row data'!$Y91+'Row data'!$Z91+'Row data'!$AA91+'Row data'!$AB91+'Row data'!$AD91-'Row data'!$AC91-'Row data'!$AE91-'Row data'!$AF91-'Row data'!$AG91-'Row data'!$AH91-'Row data'!$AI91 -> 20618 | AK91: 20618 | AL91: 0
A92: 91 | B92: ABC J (Bangladesh) Ltd. | C92: 8797049 | D92: Sharif | E92: Production | F92: Padding A | G92: Senior Operator | H92: 9993204000006600 | I92: 35254 | J92: 45066 | K92: =YEAR('Row data'!$J92) -> 2023 | L92: 28265 | M92: =IF('Row data'!$J92="",DATEDIF('Row data'!$L92,TODAY(),"y"),"0") -> 0 | N92: M | O92: N | P92: Staff | Q92: 27187 | R92: 27187 | S92: 16312 | T92: 8156 | U92: 1087 | V92: 816 | W92: 0 | X92: 0 | Y92: 816 | Z92: 816 | AA92: 0 | AB92: 0 | AC92: 0 | AD92: 0 | AE92: 0 | AF92: 0 | AG92: 0 | AH92: 0 | AI92: 0 | AJ92: ='Row data'!$S92+'Row data'!$T92+'Row data'!$U92+'Row data'!$W92+'Row data'!$X92+'Row data'!$Y92+'Row data'!$Z92+'Row data'!$AA92+'Row data'!$AB92+'Row data'!$AD92-'Row data'!$AC92-'Row data'!$AE92-'Row data'!$AF92-'Row data'!$AG92-'Row data'!$AH92-'Row data'!$AI92 -> 27187 | AK92: 27187 | AL92: 0
A93: 92 | B93: ABC J (Bangladesh) Ltd. | C93: 8718947 | D93: Shihab | E93: Production | F93: Padding A | G93: Padding Machine Operator | H93: 9993204000006560 | I93: 38353 | J93: 45048 | K93: =YEAR('Row data'!$J93) -> 2023 | L93: 32265 | M93: =IF('Row data'!$J93="",DATEDIF('Row data'!$L93,TODAY(),"y"),"0") -> 0 | N93: M | O93: N | P93: Staff | Q93: 22357 | R93: 22357 | S93: 13414 | T93: 6707 | U93: 894 | V93: 671 | W93: 0 | X93: 0 | Y93: 671 | Z93: 671 | AA93: 350 | AB93: 0 | AC93: 0 | AD93: 0 | AE93: 0 | AF93: 0 | AG93: 0 | AH93: 0 | AI93: 0 | AJ93: ='Row data'!$S93+'Row data'!$T93+'Row data'!$U93+'Row data'!$W93+'Row data'!$X93+'Row data'!$Y93+'Row data'!$Z93+'Row data'!$AA93+'Row data'!$AB93+'Row data'!$AD93-'Row data'!$AC93-'Row data'!$AE93-'Row data'!$AF93-'Row data'!$AG93-'Row data'!$AH93-'Row data'!$AI93 -> 22707 | AK93: 22707 | AL93: 0
A94: 93 | B94: ABC J (Bangladesh) Ltd. | C94: 7419442 | D94: Shohag | E94: Production | F94: Padding A | G94: Senior Carding Operator | H94: 9993204000006590 | I94: 37007 | J94: 45209 | K94: =YEAR('Row data'!$J94) -> 2023 | L94: 28408 | M94: =IF('Row data'!$J94="",DATEDIF('Row data'!$L94,TODAY(),"y"),"0") -> 0 | N94: M | O94: N | P94: Staff | Q94: 25274 | R94: 25274 | S94: 15165 | T94: 7582 | U94: 1011 | V94: 758 | W94: 0 | X94: 0 | Y94: 758 | Z94: 758 | AA94: 350 | AB94: 0 | AC94: 0 | AD94: 0 | AE94: 0 | AF94: 0 | AG94: 0 | AH94: 0 | AI94: 0 | AJ94: ='Row data'!$S94+'Row data'!$T94+'Row data'!$U94+'Row data'!$W94+'Row data'!$X94+'Row data'!$Y94+'Row data'!$Z94+'Row data'!$AA94+'Row data'!$AB94+'Row data'!$AD94-'Row data'!$AC94-'Row data'!$AE94-'Row data'!$AF94-'Row data'!$AG94-'Row data'!$AH94-'Row data'!$AI94 -> 25624 | AK94: 25624 | AL94: 0
A95: 94 | B95: ABC J (Bangladesh) Ltd. | C95: 5598582 | D95: Shuvo | E95: Production | F95: Padding A | G95: Asst. Production Incharge | H95: 703204000029563 | I95: 36173 | L95: 30440 | M95: =IF('Row data'!$J95="",DATEDIF('Row data'!$L95,TODAY(),"y"),"0") -> 43 | N95: M | O95: N | P95: Staff | Q95: 49018 | R95: 49018 | S95: 29410 | T95: 14705 | U95: 1961 | V95: 1471 | W95: 0 | X95: 0 | Y95: 1471 | Z95: 1471 | AA95: 0 | AB95: 0 | AC95: 0 | AD95: 0 | AE95: 0 | AF95: 0 | AG95: 0 | AH95: 333 | AI95: 0 | AJ95: ='Row data'!$S95+'Row data'!$T95+'Row data'!$U95+'Row data'!$W95+'Row data'!$X95+'Row data'!$Y95+'Row data'!$Z95+'Row data'!$AA95+'Row data'!$AB95+'Row data'!$AD95-'Row data'!$AC95-'Row data'!$AE95-'Row data'!$AF95-'Row data'!$AG95-'Row data'!$AH95-'Row data'!$AI95 -> 48685 | AK95: 48685 | AL95: 0
A96: 95 | B96: ABC J (Bangladesh) Ltd. | C96: 5410569 | D96: Siam | E96: Production | F96: Padding A | G96: In Charge | H96: 783204000012108 | I96: 34851 | L96: 34851 | M96: =IF('Row data'!$J96="",DATEDIF('Row data'!$L96,TODAY(),"y"),"0") -> 31 | N96: M | O96: N | P96: Staff | Q96: 88727 | R96: 88727 | S96: 53236 | T96: 26618 | U96: 3549 | V96: 2662 | W96: 0 | X96: 0 | Y96: 2662 | Z96: 2662 | AA96: 0 | AB96: 0 | AC96: 0 | AD96: 0 | AE96: 0 | AF96: 0 | AG96: 5000 | AH96: 1800 | AI96: 0 | AJ96: ='Row data'!$S96+'Row data'!$T96+'Row data'!$U96+'Row data'!$W96+'Row data'!$X96+'Row data'!$Y96+'Row data'!$Z96+'Row data'!$AA96+'Row data'!$AB96+'Row data'!$AD96-'Row data'!$AC96-'Row data'!$AE96-'Row data'!$AF96-'Row data'!$AG96-'Row data'!$AH96-'Row data'!$AI96 -> 81927 | AK96: 81927 | AL96: 0
A97: 96 | B97: ABC J (Bangladesh) Ltd. | C97: 6894601 | D97: Siraj | E97: Production | F97: Padding A | G97: Deputy Production Incharge | H97: 703204000029483 | I97: 35840 | L97: 26494 | M97: =IF('Row data'!$J97="",DATEDIF('Row data'!$L97,TODAY(),"y"),"0") -> 54 | N97: M | O97: N | P97: Staff | Q97: 57770 | R97: 57770 | S97: 34662 | T97: 17331 | U97: 2311 | V97: 1733 | W97: 0 | X97: 0 | Y97: 1733 | Z97: 1733 | AA97: 0 | AB97: 0 | AC97: 0 | AD97: 0 | AE97: 0 | AF97: 0 | AG97: 0 | AH97: 350 | AI97: 0 | AJ97: ='Row data'!$S97+'Row data'!$T97+'Row data'!$U97+'Row data'!$W97+'Row data'!$X97+'Row data'!$Y97+'Row data'!$Z97+'Row data'!$AA97+'Row data'!$AB97+'Row data'!$AD97-'Row data'!$AC97-'Row data'!$AE97-'Row data'!$AF97-'Row data'!$AG97-'Row data'!$AH97-'Row data'!$AI97 -> 57420 | AK97: 57420 | AL97: 0
A98: 97 | B98: ABC J (Bangladesh) Ltd. | C98: 5694269 | D98: Sohail | E98: Production | F98: Padding A | G98: Supervisor | H98: 703204000029381 | I98: 41441 | L98: 32970 | M98: =IF('Row data'!$J98="",DATEDIF('Row data'!$L98,TODAY(),"y"),"0") -> 36 | N98: M | O98: N | P98: Staff | Q98: 32700 | R98: 32700 | S98: 19620 | T98: 9810 | U98: 1308 | V98: 981 | W98: 0 | X98: 0 | Y98: 981 | Z98: 981 | AA98: 0 | AB98: 0 | AC98: 0 | AD98: 0 | AE98: 0 | AF98: 0 | AG98: 0 | AH98: 0 | AI98: 0 | AJ98: ='Row data'!$S98+'Row data'!$T98+'Row data'!$U98+'Row data'!$W98+'Row data'!$X98+'Row data'!$Y98+'Row data'!$Z98+'Row data'!$AA98+'Row data'!$AB98+'Row data'!$AD98-'Row data'!$AC98-'Row data'!$AE98-'Row data'!$AF98-'Row data'!$AG98-'Row data'!$AH98-'Row data'!$AI98 -> 32700 | AK98: 32700 | AL98: 0
A99: 98 | B99: ABC J (Bangladesh) Ltd. | C99: 5422664 | D99: Sohan | E99: Production | F99: Padding A | G99: Senior Quality Inspector | H99: 703204000029100 | I99: 41944 | L99: 31904 | M99: =IF('Row data'!$J99="",DATEDIF('Row data'!$L99,TODAY(),"y"),"0") -> 39 | N99: M | O99: N | P99: Staff | Q99: 19620 | R99: 19620 | S99: 11771 | T99: 5886 | U99: 785 | V99: 589 | W99: 0 | X99: 0 | Y99: 589 | Z99: 589 | AA99: 350 | AB99: 0 | AC99: 0 | AD99: 0 | AE99: 0 | AF99: 0 | AG99: 0 | AH99: 0 | AI99: 0 | AJ99: ='Row data'!$S99+'Row data'!$T99+'Row data'!$U99+'Row data'!$W99+'Row data'!$X99+'Row data'!$Y99+'Row data'!$Z99+'Row data'!$AA99+'Row data'!$AB99+'Row data'!$AD99-'Row data'!$AC99-'Row data'!$AE99-'Row data'!$AF99-'Row data'!$AG99-'Row data'!$AH99-'Row data'!$AI99 -> 19970 | AK99: 19970 | AL99: 0
A100: 99 | B100: ABC J (Bangladesh) Ltd. | C100: 8157677 | D100: Sujan | E100: Production | F100: Padding A | G100: Senior Quality Inspector | H100: 703204000029246 | I100: 42675 | L100: 29314 | M100: =IF('Row data'!$J100="",DATEDIF('Row data'!$L100,TODAY(),"y"),"0") -> 46 | N100: M | O100: N | P100: Staff | Q100: 20279 | R100: 16368 | S100: 12168 | T100: 6084 | U100: 811 | V100: 608 | W100: 0 | X100: 0 | Y100: 608 | Z100: 608 | AA100: 0 | AB100: 0 | AC100: 0 | AD100: 0 | AE100: 3911 | AF100: 0 | AG100: 1500 | AH100: 0 | AI100: 0 | AJ100: ='Row data'!$S100+'Row data'!$T100+'Row data'!$U100+'Row data'!$W100+'Row data'!$X100+'Row data'!$Y100+'Row data'!$Z100+'Row data'!$AA100+'Row data'!$AB100+'Row data'!$AD100-'Row data'!$AC100-'Row data'!$AE100-'Row data'!$AF100-'Row data'!$AG100-'Row data'!$AH100-'Row data'!$AI100 -> 14868 | AK100: 14868 | AL100: 0
A101: 100 | B101: ABC J (Bangladesh) Ltd. | C101: 7277752 | D101: Sumon | E101: Production | F101: Quality | G101: General Quality Inspector | H101: 703204000030959 | I101: 43834 | J101: 44562 | K101: =YEAR('Row data'!$J101) -> 2022 | L101: 37154 | M101: =IF('Row data'!$J101="",DATEDIF('Row data'!$L101,TODAY(),"y"),"0") -> 0 | N101: F | O101: N | P101: Staff | Q101: 16299 | R101: 16299 | S101: 9779 | T101: 4890 | U101: 652 | V101: 489 | W101: 0 | X101: 0 | Y101: 489 | Z101: 489 | AA101: 0 | AB101: 0 | AC101: 0 | AD101: 0 | AE101: 0 | AF101: 0 | AG101: 0 | AH101: 0 | AI101: 0 | AJ101: ='Row data'!$S101+'Row data'!$T101+'Row data'!$U101+'Row data'!$W101+'Row data'!$X101+'Row data'!$Y101+'Row data'!$Z101+'Row data'!$AA101+'Row data'!$AB101+'Row data'!$AD101-'Row data'!$AC101-'Row data'!$AE101-'Row data'!$AF101-'Row data'!$AG101-'Row data'!$AH101-'Row data'!$AI101 -> 16299 | AK101: 16299 | AL101: 0
A102: 101 | B102: ABC J (Bangladesh) Ltd. | C102: 6857802 | D102: Tarek | E102: Production | F102: Quality | G102: Quality Inspector | H102: 703204000030507 | I102: 42450 | J102: 44562 | K102: =YEAR('Row data'!$J102) -> 2022 | L102: 34885 | M102: =IF('Row data'!$J102="",DATEDIF('Row data'!$L102,TODAY(),"y"),"0") -> 0 | N102: M | O102: N | P102: Staff | Q102: 17406 | R102: 17406 | S102: 10444 | T102: 5222 | U102: 696 | V102: 522 | W102: 0 | X102: 0 | Y102: 522 | Z102: 522 | AA102: 0 | AB102: 0 | AC102: 0 | AD102: 0 | AE102: 0 | AF102: 0 | AG102: 0 | AH102: 0 | AI102: 0 | AJ102: ='Row data'!$S102+'Row data'!$T102+'Row data'!$U102+'Row data'!$W102+'Row data'!$X102+'Row data'!$Y102+'Row data'!$Z102+'Row data'!$AA102+'Row data'!$AB102+'Row data'!$AD102-'Row data'!$AC102-'Row data'!$AE102-'Row data'!$AF102-'Row data'!$AG102-'Row data'!$AH102-'Row data'!$AI102 -> 17406 | AK102: 17406 | AL102: 0
A103: 102 | B103: ABC J (Bangladesh) Ltd. | C103: 6822006 | D103: Tariqul | E103: Production | F103: Quality | G103: Quality Inspector | H103: 703204000030378 | I103: 41161 | J103: 44562 | K103: =YEAR('Row data'!$J103) -> 2022 | L103: 29545 | M103: =IF('Row data'!$J103="",DATEDIF('Row data'!$L103,TODAY(),"y"),"0") -> 0 | N103: M | O103: N | P103: Staff | Q103: 20054 | R103: 20054 | S103: 12032 | T103: 6016 | U103: 802 | V103: 602 | W103: 0 | X103: 0 | Y103: 602 | Z103: 602 | AA103: 0 | AB103: 0 | AC103: 0 | AD103: 0 | AE103: 0 | AF103: 0 | AG103: 0 | AH103: 0 | AI103: 0 | AJ103: ='Row data'!$S103+'Row data'!$T103+'Row data'!$U103+'Row data'!$W103+'Row data'!$X103+'Row data'!$Y103+'Row data'!$Z103+'Row data'!$AA103+'Row data'!$AB103+'Row data'!$AD103-'Row data'!$AC103-'Row data'!$AE103-'Row data'!$AF103-'Row data'!$AG103-'Row data'!$AH103-'Row data'!$AI103 -> 20054 | AK103: 20054 | AL103: 0
A104: 103 | B104: ABC J (Bangladesh) Ltd. | C104: 5336453 | D104: Towhid | E104: Production | F104: Quality | G104: General Quality Inspector | H104: 9993204000006640 | I104: 44992 | J104: 44562 | K104: =YEAR('Row data'!$J104) -> 2022 | L104: 37057 | M104: =IF('Row data'!$J104="",DATEDIF('Row data'!$L104,TODAY(),"y"),"0") -> 0 | N104: F | O104: N | P104: Staff | Q104: 16048 | R104: 8024 | S104: 9629 | T104: 4815 | U104: 642 | V104: 481 | W104: 0 | X104: 0 | Y104: 481 | Z104: 481 | AA104: 0 | AB104: 0 | AC104: -8024 | AD104: 0 | AE104: 0 | AF104: 0 | AG104: 0 | AH104: 0 | AI104: 0 | AJ104: ='Row data'!$S104+'Row data'!$T104+'Row data'!$U104+'Row data'!$W104+'Row data'!$X104+'Row data'!$Y104+'Row data'!$Z104+'Row data'!$AA104+'Row data'!$AB104+'Row data'!$AD104-'Row data'!$AC104-'Row data'!$AE104-'Row data'!$AF104-'Row data'!$AG104-'Row data'!$AH104-'Row data'!$AI104 -> 24072 | AK104: 8024 | AL104: 0
A105: 104 | B105: ABC J (Bangladesh) Ltd. | C105: 5279757 | D105: Wahid | E105: Production | F105: Quality | G105: Quality Inspector | H105: 703204000029009 | I105: 42409 | L105: 35222 | M105: =IF('Row data'!$J105="",DATEDIF('Row data'!$L105,TODAY(),"y"),"0") -> 30 | N105: M | O105: N | P105: Staff | Q105: 17136 | R105: 14136 | S105: 10282 | T105: 5141 | U105: 685 | V105: 514 | W105: 0 | X105: 0 | Y105: 514 | Z105: 514 | AA105: 0 | AB105: 0 | AC105: -3000 | AD105: 0 | AE105: 0 | AF105: 0 | AG105: 3000 | AH105: 0 | AI105: 0 | AJ105: ='Row data'!$S105+'Row data'!$T105+'Row data'!$U105+'Row data'!$W105+'Row data'!$X105+'Row data'!$Y105+'Row data'!$Z105+'Row data'!$AA105+'Row data'!$AB105+'Row data'!$AD105-'Row data'!$AC105-'Row data'!$AE105-'Row data'!$AF105-'Row data'!$AG105-'Row data'!$AH105-'Row data'!$AI105 -> 17136 | AK105: 11136 | AL105: 0
A106: 105 | B106: ABC J (Bangladesh) Ltd. | C106: 5186144 | D106: Yasin | E106: Production | F106: Quality | G106: General Quality Inspector | H106: 703204000029097 | I106: 43834 | L106: 36074 | M106: =IF('Row data'!$J106="",DATEDIF('Row data'!$L106,TODAY(),"y"),"0") -> 27 | N106: M | O106: N | P106: Staff | Q106: 16265 | R106: 16265 | S106: 9759 | T106: 4879 | U106: 651 | V106: 488 | W106: 0 | X106: 0 | Y106: 488 | Z106: 488 | AA106: 0 | AB106: 0 | AC106: 0 | AD106: 0 | AE106: 0 | AF106: 0 | AG106: 0 | AH106: 0 | AI106: 0 | AJ106: ='Row data'!$S106+'Row data'!$T106+'Row data'!$U106+'Row data'!$W106+'Row data'!$X106+'Row data'!$Y106+'Row data'!$Z106+'Row data'!$AA106+'Row data'!$AB106+'Row data'!$AD106-'Row data'!$AC106-'Row data'!$AE106-'Row data'!$AF106-'Row data'!$AG106-'Row data'!$AH106-'Row data'!$AI106 -> 16265 | AK106: 16265 | AL106: 0
...

Sheet Demo Ans
B2: 1. How many employees are currently working in the company?
B4: =SUM(COUNTA('Row data'!I2:I606)-SUM(COUNTA('Row data'!J2:J606)))& " People " -> 404 People
B6: 2. What is the gender distribution of employees?
B8: =COUNTIF('Row data'!N2:N606,"M")&" Male , " &COUNTIF('Row data'!N2:N606,"F")&" Fmale" -> 400 Male , 205 Fmale
B11: 3. What is the average age of employees Male and Female? | D11: Averageif
B13: Male | C13: =AVERAGEIF('Row data'!N2:N606,"M",'Row data'!M2:M606) -> 35.757937 | D13: Female | E13: =AVERAGEIF('Row data'!N2:N606,"F",'Row data'!M2:M606) -> 40.111842
B15: 4. How many employees joined this year?
B17: =COUNTIFS('Row data'!I2:I606,">=2025-01-01",'Row data'!I2:I606,"<=2025-12-31") -> 6
B19: 5. What is the attrition rate (employees who quit last 5 years)
B21: Year | C21: Total Quit | D21: Percentage
B22: 2025 | C22: 4 | D22: 0.019900498
B23: 2024 | C23: 10 | D23: 0.049751244
B24: 2023 | C24: 10 | D24: 0.049751244
B25: 2022 | C25: 135 | D25: 0.67164179
B26: 2021 | C26: 9 | D26: 0.044776119
B27: 2020 | C27: 7 | D27: 0.034825871
B28: 2019 | C28: 14 | D28: 0.069651741
B29: 2018 | C29: 12 | D29: 0.059701493
B33: Year | C33: Total Quit | D33: Percentage
B34: 2021 | C34: =COUNTIF('Row data'!$K$2:$K$606,B34) -> 9 | D34: =C34/COUNTIFS('Row data'!$I$2:$I$606,">=2021-01-01",'Row data'!$I$2:$I$606,"<=2021-12-31") -> 0.1125
B35: 2022 | C35: =COUNTIF('Row data'!$K$2:$K$606,B35) -> 135 | D35: =C35/COUNTIFS('Row data'!$I$2:$I$606,">=2022-01-01",'Row data'!$I$2:$I$606,"<=2022-12-31") -> 1.8243243
B36: 2023 | C36: =COUNTIF('Row data'!$K$2:$K$606,B36) -> 10 | D36: =C36/COUNTIFS('Row data'!$I$2:$I$606,">=2023-01-01",'Row data'!$I$2:$I$606,"<=2023-12-31") -> 0.12195122
B37: 2024 | C37: =COUNTIF('Row data'!$K$2:$K$606,B37) -> 10 | D37: =$C$37/COUNTIFS('Row data'!$I$2:$I$606,">=2024-01-01",'Row data'!$I$2:$I$606,"<=2024-12-31") -> 0.71428571
B38: 2025 | C38: =COUNTIF('Row data'!$K$2:$K$606,B38) -> 4 | D38: =C38/COUNTIFS('Row data'!$I$2:$I$606,">=2025-01-01",'Row data'!$I$2:$I$606,"<=2025-12-31") -> 0.66666667

Sheet Demo Ans 2
B2: 6. What is the distribution of employees by designation name? | G2: 7. What is the distribution of employees by department and designation? | L2: 8. What is the average Total in each department? | P2: 9. Which department has the highest turnover rate? (depend on the total quit employees)
G3: Department | P3: Department | Q3: Join | R3: Quit | S3: Percentage
B4: Designation | C4: Employee | D4: Distribution | G4: Production | L4: Department | M4: Avg. Gross | N4: Avg. Gross Pay | P4: {=_xlfn.UNIQUE(Row[DeptName])} -> Production | Q4: =COUNTIFS(Row[DeptName],P4,Row[JDate],">=1995-01-01",Row[JDate],"<=2025-12-31") -> 457 | R4: =COUNTIFS(Row[DeptName],P4,Row[QuitDate],">=1995-01-01",Row[QuitDate],"<=2025-12-31") -> 130 | S4: =R4/Q4 -> 0.28446389
B5: {=_xlfn.UNIQUE('Row data'!$G$2:$G$606)} -> Trainee Officer | C5: =COUNTIF('Row data'!$G$2:$G$606,'Demo Ans 2'!B7) -> 153 | D5: =C5/SUM($C$5:$C$125) -> 0.25289256 | G5: Designation | H5: Employee | I5: Distribution | L5: {=_xlfn.UNIQUE(Row[DeptName])} -> Production | M5: =AVERAGEIFS(Row[Gross],Row[DeptName],L5) -> 16202.812 | N5: =AVERAGEIFS(Row[Gross Pay],Row[DeptName],L5) -> 15991.978 | P5: Utility & Maintenance | Q5: =COUNTIFS(Row[DeptName],P5,Row[JDate],">=1995-01-01",Row[JDate],"<=2025-12-31") -> 39 | R5: =COUNTIFS(Row[DeptName],P5,Row[QuitDate],">=1995-01-01",Row[QuitDate],"<=2025-12-31") -> 12 | S5: =R5/Q5 -> 0.30769231
B6: Head Fitter | C6: =COUNTIF('Row data'!$G$2:$G$606,'Demo Ans 2'!B28) -> 67 | D6: =C6/SUM($C$5:$C$125) -> 0.1107438 | G6: {=_xlfn.UNIQUE(_xlfn._xlws.FILTER('Row data'!$G$2:$G$606,'Row data'!$E$2:$E$606='Demo Ans 2'!$G$4))} -> Trainee Officer | H6: =COUNTIFS(Row[DeptName],$G$4,Row[DesigName],G6) -> 1 | I6: =H6/COUNTA(Row[EmpId]) -> 0.0016528926 | L6: Utility & Maintenance | M6: =AVERAGEIFS(Row[Gross],Row[DeptName],L6) -> 25814.564 | N6: =AVERAGEIFS(Row[Gross Pay],Row[DeptName],L6) -> 24706.513 | P6: Admin | Q6: =COUNTIFS(Row[DeptName],P6,Row[JDate],">=1995-01-01",Row[JDate],"<=2025-12-31") -> 83 | R6: =COUNTIFS(Row[DeptName],P6,Row[QuitDate],">=1995-01-01",Row[QuitDate],"<=2025-12-31") -> 47 | S6: =R6/Q6 -> 0.56626506
B7: Assistant | C7: =COUNTIF('Row data'!$G$2:$G$606,'Demo Ans 2'!B29) -> 42 | D7: =C7/SUM($C$5:$C$125) -> 0.069421488 | G7: Head Fitter | H7: =COUNTIFS(Row[DeptName],$G$4,Row[DesigName],G7) -> 1 | I7: =H7/COUNTA(Row[EmpId]) -> 0.0016528926 | L7: Admin | M7: =AVERAGEIFS(Row[Gross],Row[DeptName],L7) -> 21231.843 | N7: =AVERAGEIFS(Row[Gross Pay],Row[DeptName],L7) -> 20595.157 | P7: Delivery | Q7: =COUNTIFS(Row[DeptName],P7,Row[JDate],">=1995-01-01",Row[JDate],"<=2025-12-31") -> 6 | R7: =COUNTIFS(Row[DeptName],P7,Row[QuitDate],">=1995-01-01",Row[QuitDate],"<=2025-12-31") -> 2 | S7: =R7/Q7 -> 0.33333333
B8: Senior Fitter | C8: =COUNTIF('Row data'!$G$2:$G$606,'Demo Ans 2'!B92) -> 34 | D8: =C8/SUM($C$5:$C$125) -> 0.056198347 | G8: Assistant | H8: =COUNTIFS(Row[DeptName],$G$4,Row[DesigName],G8) -> 148 | I8: =H8/COUNTA(Row[EmpId]) -> 0.2446281 | L8: Delivery | M8: =AVERAGEIFS(Row[Gross],Row[DeptName],L8) -> 33999.5 | N8: =AVERAGEIFS(Row[Gross Pay],Row[DeptName],L8) -> 33166.167 | P8: HR & Compliance | Q8: =COUNTIFS(Row[DeptName],P8,Row[JDate],">=1995-01-01",Row[JDate],"<=2025-12-31") -> 4 | R8: =COUNTIFS(Row[DeptName],P8,Row[QuitDate],">=1995-01-01",Row[QuitDate],"<=2025-12-31") -> 0 | S8: =R8/Q8 -> 0
B9: Shift Engineer | C9: =COUNTIF('Row data'!$G$2:$G$606,'Demo Ans 2'!B23) -> 14 | D9: =C9/SUM($C$5:$C$125) -> 0.023140496 | G9: Senior Fitter | H9: =COUNTIFS(Row[DeptName],$G$4,Row[DesigName],G9) -> 1 | I9: =H9/COUNTA(Row[EmpId]) -> 0.0016528926 | L9: HR & Compliance | M9: =AVERAGEIFS(Row[Gross],Row[DeptName],L9) -> 32836.5 | N9: =AVERAGEIFS(Row[Gross Pay],Row[DeptName],L9) -> 31586.5 | P9: IT | Q9: =COUNTIFS(Row[DeptName],P9,Row[JDate],">=1995-01-01",Row[JDate],"<=2025-12-31") -> 2 | R9: =COUNTIFS(Row[DeptName],P9,Row[QuitDate],">=1995-01-01",Row[QuitDate],"<=2025-12-31") -> 1 | S9: =R9/Q9 -> 0.5
B10: Senior Supervisor | C10: =COUNTIF('Row data'!$G$2:$G$606,'Demo Ans 2'!B49) -> 13 | D10: =C10/SUM($C$5:$C$125) -> 0.021487603 | G10: Shift Engineer | H10: =COUNTIFS(Row[DeptName],$G$4,Row[DesigName],G10) -> 5 | I10: =H10/COUNTA(Row[EmpId]) -> 0.0082644628 | L10: IT | M10: =AVERAGEIFS(Row[Gross],Row[DeptName],L10) -> 41420 | N10: =AVERAGEIFS(Row[Gross Pay],Row[DeptName],L10) -> 41420 | P10: Store | Q10: =COUNTIFS(Row[DeptName],P10,Row[JDate],">=1995-01-01",Row[JDate],"<=2025-12-31") -> 12 | R10: =COUNTIFS(Row[DeptName],P10,Row[QuitDate],">=1995-01-01",Row[QuitDate],"<=2025-12-31") -> 8 | S10: =R10/Q10 -> 0.66666667
B11: Junior Executive | C11: =COUNTIF('Row data'!$G$2:$G$606,'Demo Ans 2'!B27) -> 11 | D11: =C11/SUM($C$5:$C$125) -> 0.018181818 | G11: Senior Supervisor | H11: =COUNTIFS(Row[DeptName],$G$4,Row[DesigName],G11) -> 7 | I11: =H11/COUNTA(Row[EmpId]) -> 0.011570248 | L11: Store | M11: =AVERAGEIFS(Row[Gross],Row[DeptName],L11) -> 20718.417 | N11: =AVERAGEIFS(Row[Gross Pay],Row[DeptName],L11) -> 19604.583 | P11: Accounts | Q11: =COUNTIFS(Row[DeptName],P11,Row[JDate],">=1995-01-01",Row[JDate],"<=2025-12-31") -> 2 | R11: =COUNTIFS(Row[DeptName],P11,Row[QuitDate],">=1995-01-01",Row[QuitDate],"<=2025-12-31") -> 1 | S11: =R11/Q11 -> 0.5
B12: Assistant Cook | C12: =COUNTIF('Row data'!$G$2:$G$606,'Demo Ans 2'!B16) -> 10 | D12: =C12/SUM($C$5:$C$125) -> 0.016528926 | G12: Trainee Shift Engineer | H12: =COUNTIFS(Row[DeptName],$G$4,Row[DesigName],G12) -> 1 | I12: =H12/COUNTA(Row[EmpId]) -> 0.0016528926 | L12: Accounts | M12: =AVERAGEIFS(Row[Gross],Row[DeptName],L12) -> 47905.5 | N12: =AVERAGEIFS(Row[Gross Pay],Row[DeptName],L12) -> 47905.5
B13: Cook | C13: =COUNTIF('Row data'!$G$2:$G$606,'Demo Ans 2'!B17) -> 10 | D13: =C13/SUM($C$5:$C$125) -> 0.016528926 | G13: Sr. Shift Engineer | H13: =COUNTIFS(Row[DeptName],$G$4,Row[DesigName],G13) -> 1 | I13: =H13/COUNTA(Row[EmpId]) -> 0.0016528926
B14: Deputy General Manager | C14: =COUNTIF('Row data'!$G$2:$G$606,'Demo Ans 2'!B66) -> 9 | D14: =C14/SUM($C$5:$C$125) -> 0.014876033 | G14: Assistant Bundleman | H14: =COUNTIFS(Row[DeptName],$G$4,Row[DesigName],G14) -> 14 | I14: =H14/COUNTA(Row[EmpId]) -> 0.023140496
B15: Lady Checker | C15: =COUNTIF('Row data'!$G$2:$G$606,'Demo Ans 2'!B78) -> 9 | D15: =C15/SUM($C$5:$C$125) -> 0.014876033 | G15: Designer | H15: =COUNTIFS(Row[DeptName],$G$4,Row[DesigName],G15) -> 1 | I15: =H15/COUNTA(Row[EmpId]) -> 0.0016528926
B16: Loader | C16: =COUNTIF('Row data'!$G$2:$G$606,'Demo Ans 2'!B83) -> 8 | D16: =C16/SUM($C$5:$C$125) -> 0.01322314 | G16: Supervisor | H16: =COUNTIFS(Row[DeptName],$G$4,Row[DesigName],G16) -> 5 | I16: =H16/COUNTA(Row[EmpId]) -> 0.0082644628
B17: Driver | C17: =COUNTIF('Row data'!$G$2:$G$606,'Demo Ans 2'!B93) -> 8 | D17: =C17/SUM($C$5:$C$125) -> 0.01322314 | G17: Laser Cutting Machine Operator | H17: =COUNTIFS(Row[DeptName],$G$4,Row[DesigName],G17) -> 1 | I17: =H17/COUNTA(Row[EmpId]) -> 0.0016528926
B18: Assistant Forklift Driver | C18: =COUNTIF('Row data'!$G$2:$G$606,'Demo Ans 2'!B10) -> 7 | D18: =C18/SUM($C$5:$C$125) -> 0.011570248 | G18: Quality Inspector | H18: =COUNTIFS(Row[DeptName],$G$4,Row[DesigName],G18) -> 11 | I18: =H18/COUNTA(Row[EmpId]) -> 0.018181818
B19: Asst. Admin Officer | C19: =COUNTIF('Row data'!$G$2:$G$606,'Demo Ans 2'!B69) -> 7 | D19: =C19/SUM($C$5:$C$125) -> 0.011570248 | G19: Operator | H19: =COUNTIFS(Row[DeptName],$G$4,Row[DesigName],G19) -> 66 | I19: =H19/COUNTA(Row[EmpId]) -> 0.10909091
B20: Executive | C20: =COUNTIF('Row data'!$G$2:$G$606,'Demo Ans 2'!B85) -> 7 | D20: =C20/SUM($C$5:$C$125) -> 0.011570248 | G20: Assistant Operator | H20: =COUNTIFS(Row[DeptName],$G$4,Row[DesigName],G20) -> 42 | I20: =H20/COUNTA(Row[EmpId]) -> 0.069421488
B21: Trainee Shift Engineer | C21: =COUNTIF('Row data'!$G$2:$G$606,'Demo Ans 2'!B97) -> 7 | D21: =C21/SUM($C$5:$C$125) -> 0.011570248 | G21: Assistant Supervisor | H21: =COUNTIFS(Row[DeptName],$G$4,Row[DesigName],G21) -> 2 | I21: =H21/COUNTA(Row[EmpId]) -> 0.0033057851
B22: Sr. Shift Engineer | C22: =COUNTIF('Row data'!$G$2:$G$606,'Demo Ans 2'!B9) -> 6 | D22: =C22/SUM($C$5:$C$125) -> 0.0099173554 | G22: Mechanic | H22: =COUNTIFS(Row[DeptName],$G$4,Row[DesigName],G22) -> 2 | I22: =H22/COUNTA(Row[EmpId]) -> 0.0033057851
B23: Assistant Bundleman | C23: =COUNTIF('Row data'!$G$2:$G$606,'Demo Ans 2'!B32) -> 6 | D23: =C23/SUM($C$5:$C$125) -> 0.0099173554 | G23: General Quality Inspector | H23: =COUNTIFS(Row[DeptName],$G$4,Row[DesigName],G23) -> 6 | I23: =H23/COUNTA(Row[EmpId]) -> 0.0099173554
B24: Designer | C24: =COUNTIF('Row data'!$G$2:$G$606,'Demo Ans 2'!B25) -> 5 | D24: =C24/SUM($C$5:$C$125) -> 0.0082644628 | G24: Senior Packingman | H24: =COUNTIFS(Row[DeptName],$G$4,Row[DesigName],G24) -> 1 | I24: =H24/COUNTA(Row[EmpId]) -> 0.0016528926
B25: Supervisor | C25: =COUNTIF('Row data'!$G$2:$G$606,'Demo Ans 2'!B64) -> 5 | D25: =C25/SUM($C$5:$C$125) -> 0.0082644628 | G25: Senior Operator | H25: =COUNTIFS(Row[DeptName],$G$4,Row[DesigName],G25) -> 2 | I25: =H25/COUNTA(Row[EmpId]) -> 0.0033057851
B26: Laser Cutting Machine Operator | C26: =COUNTIF('Row data'!$G$2:$G$606,'Demo Ans 2'!B86) -> 5 | D26: =C26/SUM($C$5:$C$125) -> 0.0082644628 | G26: Padding Machine Operator | H26: =COUNTIFS(Row[DeptName],$G$4,Row[DesigName],G26) -> 3 | I26: =H26/COUNTA(Row[EmpId]) -> 0.0049586777
B27: Quality Inspector | C27: =COUNTIF('Row data'!$G$2:$G$606,'Demo Ans 2'!B5) -> 4 | D27: =C27/SUM($C$5:$C$125) -> 0.0066115702 | G27: Senior Carding Operator | H27: =COUNTIFS(Row[DeptName],$G$4,Row[DesigName],G27) -> 1 | I27: =H27/COUNTA(Row[EmpId]) -> 0.0016528926
B28: Operator | C28: =COUNTIF('Row data'!$G$2:$G$606,'Demo Ans 2'!B12) -> 4 | D28: =C28/SUM($C$5:$C$125) -> 0.0066115702 | G28: Asst. Production Incharge | H28: =COUNTIFS(Row[DeptName],$G$4,Row[DesigName],G28) -> 1 | I28: =H28/COUNTA(Row[EmpId]) -> 0.0016528926
B29: Assistant Operator | C29: =COUNTIF('Row data'!$G$2:$G$606,'Demo Ans 2'!B35) -> 4 | D29: =C29/SUM($C$5:$C$125) -> 0.0066115702 | G29: In Charge | H29: =COUNTIFS(Row[DeptName],$G$4,Row[DesigName],G29) -> 2 | I29: =H29/COUNTA(Row[EmpId]) -> 0.0033057851
B30: Assistant Supervisor | C30: =COUNTIF('Row data'!$G$2:$G$606,'Demo Ans 2'!B36) -> 4 | D30: =C30/SUM($C$5:$C$125) -> 0.0066115702 | G30: Deputy Production Incharge | H30: =COUNTIFS(Row[DeptName],$G$4,Row[DesigName],G30) -> 1 | I30: =H30/COUNTA(Row[EmpId]) -> 0.0016528926
B31: Mechanic | C31: =COUNTIF('Row data'!$G$2:$G$606,'Demo Ans 2'!B90) -> 4 | D31: =C31/SUM($C$5:$C$125) -> 0.0066115702 | G31: Senior Quality Inspector | H31: =COUNTIFS(Row[DeptName],$G$4,Row[DesigName],G31) -> 2 | I31: =H31/COUNTA(Row[EmpId]) -> 0.0033057851
B32: General Quality Inspector | C32: =COUNTIF('Row data'!$G$2:$G$606,'Demo Ans 2'!B107) -> 4 | D32: =C32/SUM($C$5:$C$125) -> 0.0066115702 | G32: Asst. Production Coordinator | H32: =COUNTIFS(Row[DeptName],$G$4,Row[DesigName],G32) -> 1 | I32: =H32/COUNTA(Row[EmpId]) -> 0.0016528926
B33: Store Co-Ordinator(Assistant) | C33: =COUNTIF('Row data'!$G$2:$G$606,'Demo Ans 2'!B123) -> 4 | D33: =C33/SUM($C$5:$C$125) -> 0.0066115702 | G33: Senior Padding Machine Operator | H33: =COUNTIFS(Row[DeptName],$G$4,Row[DesigName],G33) -> 1 | I33: =H33/COUNTA(Row[EmpId]) -> 0.0016528926
B34: Store Officer | C34: =COUNTIF('Row data'!$G$2:$G$606,'Demo Ans 2'!B22) -> 3 | D34: =C34/SUM($C$5:$C$125) -> 0.0049586777 | G34: Winder Machine Operator | H34: =COUNTIFS(Row[DeptName],$G$4,Row[DesigName],G34) -> 2 | I34: =H34/COUNTA(Row[EmpId]) -> 0.0033057851
B35: Junior Executive (Electrical) | C35: =COUNTIF('Row data'!$G$2:$G$606,'Demo Ans 2'!B33) -> 3 | D35: =C35/SUM($C$5:$C$125) -> 0.0049586777 | G35: Mechanic Helper | H35: =COUNTIFS(Row[DeptName],$G$4,Row[DesigName],G35) -> 1 | I35: =H35/COUNTA(Row[EmpId]) -> 0.0016528926
B36: Assistant Electrician | C36: =COUNTIF('Row data'!$G$2:$G$606,'Demo Ans 2'!B40) -> 3 | D36: =C36/SUM($C$5:$C$125) -> 0.0049586777 | G36: Executive Procurement | H36: =COUNTIFS(Row[DeptName],$G$4,Row[DesigName],G36) -> 1 | I36: =H36/COUNTA(Row[EmpId]) -> 0.0016528926
B37: Electrician | C37: =COUNTIF('Row data'!$G$2:$G$606,'Demo Ans 2'!B42) -> 3 | D37: =C37/SUM($C$5:$C$125) -> 0.0049586777 | G37: Asst. Supervisor | H37: =COUNTIFS(Row[DeptName],$G$4,Row[DesigName],G37) -> 1 | I37: =H37/COUNTA(Row[EmpId]) -> 0.0016528926
B38: Maintenance Officer | C38: =COUNTIF('Row data'!$G$2:$G$606,'Demo Ans 2'!B43) -> 3 | D38: =C38/SUM($C$5:$C$125) -> 0.0049586777 | G38: Assistant Bale Breaker Machine Operator | H38: =COUNTIFS(Row[DeptName],$G$4,Row[DesigName],G38) -> 7 | I38: =H38/COUNTA(Row[EmpId]) -> 0.011570248
B39: Asst. Manager | C39: =COUNTIF('Row data'!$G$2:$G$606,'Demo Ans 2'!B56) -> 3 | D39: =C39/SUM($C$5:$C$125) -> 0.0049586777 | G39: Cleaner | H39: =COUNTIFS(Row[DeptName],$G$4,Row[DesigName],G39) -> 3 | I39: =H39/COUNTA(Row[EmpId]) -> 0.0049586777
B40: Assistant Fitter Man | C40: =COUNTIF('Row data'!$G$2:$G$606,'Demo Ans 2'!B101) -> 3 | D40: =C40/SUM($C$5:$C$125) -> 0.0049586777 | G40: Assistant Winder Machine Operator | H40: =COUNTIFS(Row[DeptName],$G$4,Row[DesigName],G40) -> 5 | I40: =H40/COUNTA(Row[EmpId]) -> 0.0082644628
B41: Mechanical Fitter Man | C41: =COUNTIF('Row data'!$G$2:$G$606,'Demo Ans 2'!B104) -> 3 | D41: =C41/SUM($C$5:$C$125) -> 0.0049586777 | G41: General Winder Machine Operator | H41: =COUNTIFS(Row[DeptName],$G$4,Row[DesigName],G41) -> 1 | I41: =H41/COUNTA(Row[EmpId]) -> 0.0016528926
B42: Senior Executive | C42: =COUNTIF('Row data'!$G$2:$G$606,'Demo Ans 2'!B105) -> 3 | D42: =C42/SUM($C$5:$C$125) -> 0.0049586777 | G42: General Bale Breaker Machine Operator | H42: =COUNTIFS(Row[DeptName],$G$4,Row[DesigName],G42) -> 1 | I42: =H42/COUNTA(Row[EmpId]) -> 0.0016528926
B43: Assistant Manager | C43: =COUNTIF('Row data'!$G$2:$G$606,'Demo Ans 2'!B108) -> 3 | D43: =C43/SUM($C$5:$C$125) -> 0.0049586777 | G43: Cutter Man | H43: =COUNTIFS(Row[DeptName],$G$4,Row[DesigName],G43) -> 2 | I43: =H43/COUNTA(Row[EmpId]) -> 0.0033057851
B44: Canteen Boy | C44: =COUNTIF('Row data'!$G$2:$G$606,'Demo Ans 2'!B112) -> 3 | D44: =C44/SUM($C$5:$C$125) -> 0.0049586777 | G44: Asst. Lay Women | H44: =COUNTIFS(Row[DeptName],$G$4,Row[DesigName],G44) -> 4 | I44: =H44/COUNTA(Row[EmpId]) -> 0.0066115702
B45: Governess | C45: =COUNTIF('Row data'!$G$2:$G$606,'Demo Ans 2'!B114) -> 3 | D45: =C45/SUM($C$5:$C$125) -> 0.0049586777 | G45: Junior Crush Machine Operator | H45: =COUNTIFS(Row[DeptName],$G$4,Row[DesigName],G45) -> 1 | I45: =H45/COUNTA(Row[EmpId]) -> 0.0016528926
B46: General Manager | C46: =COUNTIF('Row data'!$G$2:$G$606,'Demo Ans 2'!B6) -> 2 | D46: =C46/SUM($C$5:$C$125) -> 0.0033057851 | G46: Assistant Sewing Machine Operator | H46: =COUNTIFS(Row[DeptName],$G$4,Row[DesigName],G46) -> 34 | I46: =H46/COUNTA(Row[EmpId]) -> 0.056198347
B47: Nurse | C47: =COUNTIF('Row data'!$G$2:$G$606,'Demo Ans 2'!B11) -> 2 | D47: =C47/SUM($C$5:$C$125) -> 0.0033057851 | G47: Sewing Machine Operator | H47: =COUNTIFS(Row[DeptName],$G$4,Row[DesigName],G47) -> 8 | I47: =H47/COUNTA(Row[EmpId]) -> 0.01322314
B48: Security Trainee Supervisor | C48: =COUNTIF('Row data'!$G$2:$G$606,'Demo Ans 2'!B15) -> 2 | D48: =C48/SUM($C$5:$C$125) -> 0.0033057851 | G48: Asst. Cutter Man | H48: =COUNTIFS(Row[DeptName],$G$4,Row[DesigName],G48) -> 1 | I48: =H48/COUNTA(Row[EmpId]) -> 0.0016528926
B49: Security Guard | C49: =COUNTIF('Row data'!$G$2:$G$606,'Demo Ans 2'!B20) -> 2 | D49: =C49/SUM($C$5:$C$125) -> 0.0033057851 | G49: Embroidery Machine Operator | H49: =COUNTIFS(Row[DeptName],$G$4,Row[DesigName],G49) -> 1 | I49: =H49/COUNTA(Row[EmpId]) -> 0.0016528926
B50: Security In charge | C50: =COUNTIF('Row data'!$G$2:$G$606,'Demo Ans 2'!B30) -> 2 | D50: =C50/SUM($C$5:$C$125) -> 0.0033057851 | G50: Sample Man | H50: =COUNTIFS(Row[DeptName],$G$4,Row[DesigName],G50) -> 1 | I50: =H50/COUNTA(Row[EmpId]) -> 0.0016528926
B51: Lift Operator | C51: =COUNTIF('Row data'!$G$2:$G$606,'Demo Ans 2'!B31) -> 2 | D51: =C51/SUM($C$5:$C$125) -> 0.0033057851 | G51: Junior Operator | H51: =COUNTIFS(Row[DeptName],$G$4,Row[DesigName],G51) -> 7 | I51: =H51/COUNTA(Row[EmpId]) -> 0.011570248
B52: Asst. Manager Operation (Bottle & Logistic Support | C52: =COUNTIF('Row data'!$G$2:$G$606,'Demo Ans 2'!B34) -> 2 | D52: =C52/SUM($C$5:$C$125) -> 0.0033057851 | G52: Junior Sewing Machine Operator | H52: =COUNTIFS(Row[DeptName],$G$4,Row[DesigName],G52) -> 1 | I52: =H52/COUNTA(Row[EmpId]) -> 0.0016528926
B53: Delivery Executive | C53: =COUNTIF('Row data'!$G$2:$G$606,'Demo Ans 2'!B53) -> 2 | D53: =C53/SUM($C$5:$C$125) -> 0.0033057851 | G53: Lay Women | H53: =COUNTIFS(Row[DeptName],$G$4,Row[DesigName],G53) -> 1 | I53: =H53/COUNTA(Row[EmpId]) -> 0.0016528926
B54: Senior Packingman | C54: =COUNTIF('Row data'!$G$2:$G$606,'Demo Ans 2'!B55) -> 2 | D54: =C54/SUM($C$5:$C$125) -> 0.0033057851 | G54: Assistant Cutter | H54: =COUNTIFS(Row[DeptName],$G$4,Row[DesigName],G54) -> 2 | I54: =H54/COUNTA(Row[EmpId]) -> 0.0033057851
B55: Senior Operator | C55: =COUNTIF('Row data'!$G$2:$G$606,'Demo Ans 2'!B59) -> 2 | D55: =C55/SUM($C$5:$C$125) -> 0.0033057851 | G55: Junior Cutter | H55: =COUNTIFS(Row[DeptName],$G$4,Row[DesigName],G55) -> 1 | I55: =H55/COUNTA(Row[EmpId]) -> 0.0016528926
B56: Padding Machine Operator | C56: =COUNTIF('Row data'!$G$2:$G$606,'Demo Ans 2'!B61) -> 2 | D56: =C56/SUM($C$5:$C$125) -> 0.0033057851 | G56: Assistant Bundle Man | H56: =COUNTIFS(Row[DeptName],$G$4,Row[DesigName],G56) -> 3 | I56: =H56/COUNTA(Row[EmpId]) -> 0.0049586777
B57: Senior Carding Operator | C57: =COUNTIF('Row data'!$G$2:$G$606,'Demo Ans 2'!B68) -> 2 | D57: =C57/SUM($C$5:$C$125) -> 0.0033057851 | G57: Packing Man | H57: =COUNTIFS(Row[DeptName],$G$4,Row[DesigName],G57) -> 3 | I57: =H57/COUNTA(Row[EmpId]) -> 0.0049586777
B58: Asst. Production Incharge | C58: =COUNTIF('Row data'!$G$2:$G$606,'Demo Ans 2'!B73) -> 2 | D58: =C58/SUM($C$5:$C$125) -> 0.0033057851 | G58: Assistant Finishing Man | H58: =COUNTIFS(Row[DeptName],$G$4,Row[DesigName],G58) -> 2 | I58: =H58/COUNTA(Row[EmpId]) -> 0.0033057851
B59: In Charge | C59: =COUNTIF('Row data'!$G$2:$G$606,'Demo Ans 2'!B82) -> 2 | D59: =C59/SUM($C$5:$C$125) -> 0.0033057851 | G59: Assistant Winder Operator | H59: =COUNTIFS(Row[DeptName],$G$4,Row[DesigName],G59) -> 4 | I59: =H59/COUNTA(Row[EmpId]) -> 0.0066115702
B60: Deputy Production Incharge | C60: =COUNTIF('Row data'!$G$2:$G$606,'Demo Ans 2'!B89) -> 2 | D60: =C60/SUM($C$5:$C$125) -> 0.0033057851 | G60: Bale Breaker Machine Operator | H60: =COUNTIFS(Row[DeptName],$G$4,Row[DesigName],G60) -> 3 | I60: =H60/COUNTA(Row[EmpId]) -> 0.0049586777
B61: Senior Quality Inspector | C61: =COUNTIF('Row data'!$G$2:$G$606,'Demo Ans 2'!B102) -> 2 | D61: =C61/SUM($C$5:$C$125) -> 0.0033057851 | G61: Junior bale breaker machine operator | H61: =COUNTIFS(Row[DeptName],$G$4,Row[DesigName],G61) -> 1 | I61: =H61/COUNTA(Row[EmpId]) -> 0.0016528926
B62: Asst. Production Officer | C62: =COUNTIF('Row data'!$G$2:$G$606,'Demo Ans 2'!B106) -> 2 | D62: =C62/SUM($C$5:$C$125) -> 0.0033057851 | G62: Junior Resin Mix. Operator | H62: =COUNTIFS(Row[DeptName],$G$4,Row[DesigName],G62) -> 1 | I62: =H62/COUNTA(Row[EmpId]) -> 0.0016528926
B63: Chief Mechanic | C63: =COUNTIF('Row data'!$G$2:$G$606,'Demo Ans 2'!B122) -> 2 | D63: =C63/SUM($C$5:$C$125) -> 0.0033057851 | G63: Assistant Rolling Man | H63: =COUNTIFS(Row[DeptName],$G$4,Row[DesigName],G63) -> 1 | I63: =H63/COUNTA(Row[EmpId]) -> 0.0016528926
B64: Junior Security Guard | C64: =COUNTIF('Row data'!$G$2:$G$606,'Demo Ans 2'!B8) -> 1 | D64: =C64/SUM($C$5:$C$125) -> 0.0016528926 | G64: Rolling Man | H64: =COUNTIFS(Row[DeptName],$G$4,Row[DesigName],G64) -> 3 | I64: =H64/COUNTA(Row[EmpId]) -> 0.0049586777
B65: Security Supervisor | C65: =COUNTIF('Row data'!$G$2:$G$606,'Demo Ans 2'!B13) -> 1 | D65: =C65/SUM($C$5:$C$125) -> 0.0016528926 | G65: Loader | H65: =COUNTIFS(Row[DeptName],$G$4,Row[DesigName],G65) -> 3 | I65: =H65/COUNTA(Row[EmpId]) -> 0.0049586777
B66: Assistant delivery man | C66: =COUNTIF('Row data'!$G$2:$G$606,'Demo Ans 2'!B14) -> 1 | D66: =C66/SUM($C$5:$C$125) -> 0.0016528926 | G66: Asst. Quilting Machine Operator | H66: =COUNTIFS(Row[DeptName],$G$4,Row[DesigName],G66) -> 1 | I66: =H66/COUNTA(Row[EmpId]) -> 0.0016528926
B67: Sample Machinist | C67: =COUNTIF('Row data'!$G$2:$G$606,'Demo Ans 2'!B18) -> 1 | D67: =C67/SUM($C$5:$C$125) -> 0.0016528926 | G67: Quilting Machine Operator | H67: =COUNTIFS(Row[DeptName],$G$4,Row[DesigName],G67) -> 3 | I67: =H67/COUNTA(Row[EmpId]) -> 0.0049586777
B68: Peon | C68: =COUNTIF('Row data'!$G$2:$G$606,'Demo Ans 2'!B19) -> 1 | D68: =C68/SUM($C$5:$C$125) -> 0.0016528926 | G68: General Quality | H68: =COUNTIFS(Row[DeptName],$G$4,Row[DesigName],G68) -> 1 | I68: =H68/COUNTA(Row[EmpId]) -> 0.0016528926
B69: Asst. Driver | C69: =COUNTIF('Row data'!$G$2:$G$606,'Demo Ans 2'!B21) -> 1 | D69: =C69/SUM($C$5:$C$125) -> 0.0016528926 | G69: Junior Winder Operator | H69: =COUNTIFS(Row[DeptName],$G$4,Row[DesigName],G69) -> 1 | I69: =H69/COUNTA(Row[EmpId]) -> 0.0016528926
B70: Delivery Executive (VAT) | C70: =COUNTIF('Row data'!$G$2:$G$606,'Demo Ans 2'!B24) -> 1 | D70: =C70/SUM($C$5:$C$125) -> 0.0016528926 | G70: Resin Mix Machine Operator | H70: =COUNTIFS(Row[DeptName],$G$4,Row[DesigName],G70) -> 1 | I70: =H70/COUNTA(Row[EmpId]) -> 0.0016528926
B71: Asst. Production Coordinator | C71: =COUNTIF('Row data'!$G$2:$G$606,'Demo Ans 2'!B26) -> 1 | D71: =C71/SUM($C$5:$C$125) -> 0.0016528926 | G71: Assistant Carding Machine Operator | H71: =COUNTIFS(Row[DeptName],$G$4,Row[DesigName],G71) -> 1 | I71: =H71/COUNTA(Row[EmpId]) -> 0.0016528926
B72: Senior Padding Machine Operator | C72: =COUNTIF('Row data'!$G$2:$G$606,'Demo Ans 2'!B37) -> 1 | D72: =C72/SUM($C$5:$C$125) -> 0.0016528926 | G72: General Bale Breaker Machine Operator | H72: =COUNTIFS(Row[DeptName],$G$4,Row[DesigName],G72) -> 1 | I72: =H72/COUNTA(Row[EmpId]) -> 0.0016528926
B73: Winder Machine Operator | C73: =COUNTIF('Row data'!$G$2:$G$606,'Demo Ans 2'!B38) -> 1 | D73: =C73/SUM($C$5:$C$125) -> 0.0016528926 | G73: Assistant Rolling-man | H73: =COUNTIFS(Row[DeptName],$G$4,Row[DesigName],G73) -> 2 | I73: =H73/COUNTA(Row[EmpId]) -> 0.0033057851
B74: Mechanic Helper | C74: =COUNTIF('Row data'!$G$2:$G$606,'Demo Ans 2'!B39) -> 1 | D74: =C74/SUM($C$5:$C$125) -> 0.0016528926 | G74: Bottle Cutting Man | H74: =COUNTIFS(Row[DeptName],$G$4,Row[DesigName],G74) -> 4 | I74: =H74/COUNTA(Row[EmpId]) -> 0.0066115702
B75: Asst. Executive (Sales & Marketing) | C75: =COUNTIF('Row data'!$G$2:$G$606,'Demo Ans 2'!B41) -> 1 | D75: =C75/SUM($C$5:$C$125) -> 0.0016528926 | G75: Wash machine operator | H75: =COUNTIFS(Row[DeptName],$G$4,Row[DesigName],G75) -> 1 | I75: =H75/COUNTA(Row[EmpId]) -> 0.0016528926
B76: Asst. Service Engineer Generator | C76: =COUNTIF('Row data'!$G$2:$G$606,'Demo Ans 2'!B44) -> 1 | D76: =C76/SUM($C$5:$C$125) -> 0.0016528926 | G76: Asst. Drayer machine operator | H76: =COUNTIFS(Row[DeptName],$G$4,Row[DesigName],G76) -> 1 | I76: =H76/COUNTA(Row[EmpId]) -> 0.0016528926
B77: Fitterman | C77: =COUNTIF('Row data'!$G$2:$G$606,'Demo Ans 2'!B45) -> 1 | D77: =C77/SUM($C$5:$C$125) -> 0.0016528926
B78: Assistant Fitter Man | C78: =COUNTIF('Row data'!$G$2:$G$606,'Demo Ans 2'!B46) -> 1 | D78: =C78/SUM($C$5:$C$125) -> 0.0016528926
B79: Leath Man | C79: =COUNTIF('Row data'!$G$2:$G$606,'Demo Ans 2'!B47) -> 1 | D79: =C79/SUM($C$5:$C$125) -> 0.0016528926
B80: Executive Procurement | C80: =COUNTIF('Row data'!$G$2:$G$606,'Demo Ans 2'!B48) -> 1 | D80: =C80/SUM($C$5:$C$125) -> 0.0016528926
B81: Asst. Supervisor | C81: =COUNTIF('Row data'!$G$2:$G$606,'Demo Ans 2'!B50) -> 1 | D81: =C81/SUM($C$5:$C$125) -> 0.0016528926
B82: Assistant Scale Operator | C82: =COUNTIF('Row data'!$G$2:$G$606,'Demo Ans 2'!B51) -> 1 | D82: =C82/SUM($C$5:$C$125) -> 0.0016528926
B83: Cleaner | C83: =COUNTIF('Row data'!$G$2:$G$606,'Demo Ans 2'!B52) -> 1 | D83: =C83/SUM($C$5:$C$125) -> 0.0016528926
B84: Sweeper | C84: =COUNTIF('Row data'!$G$2:$G$606,'Demo Ans 2'!B54) -> 1 | D84: =C84/SUM($C$5:$C$125) -> 0.0016528926
B85: Assistant Bale Breaker Machine Operator | C85: =COUNTIF('Row data'!$G$2:$G$606,'Demo Ans 2'!B57) -> 1 | D85: =C85/SUM($C$5:$C$125) -> 0.0016528926
B86: Assistant Winder Machine Operator | C86: =COUNTIF('Row data'!$G$2:$G$606,'Demo Ans 2'!B58) -> 1 | D86: =C86/SUM($C$5:$C$125) -> 0.0016528926
B87: General Winder Machine Operator | C87: =COUNTIF('Row data'!$G$2:$G$606,'Demo Ans 2'!B60) -> 1 | D87: =C87/SUM($C$5:$C$125) -> 0.0016528926
B88: General Bale Breaker Machine Operator | C88: =COUNTIF('Row data'!$G$2:$G$606,'Demo Ans 2'!B62) -> 1 | D88: =C88/SUM($C$5:$C$125) -> 0.0016528926
B89: Cutter Man | C89: =COUNTIF('Row data'!$G$2:$G$606,'Demo Ans 2'!B63) -> 1 | D89: =C89/SUM($C$5:$C$125) -> 0.0016528926
B90: Asst. Lay Women | C90: =COUNTIF('Row data'!$G$2:$G$606,'Demo Ans 2'!B65) -> 1 | D90: =C90/SUM($C$5:$C$125) -> 0.0016528926
B91: Junior Crush Machine Operator | C91: =COUNTIF('Row data'!$G$2:$G$606,'Demo Ans 2'!B67) -> 1 | D91: =C91/SUM($C$5:$C$125) -> 0.0016528926
B92: Assistant Sewing Machine Operator | C92: =COUNTIF('Row data'!$G$2:$G$606,'Demo Ans 2'!B70) -> 1 | D92: =C92/SUM($C$5:$C$125) -> 0.0016528926
B93: Sewing Machine Operator | C93: =COUNTIF('Row data'!$G$2:$G$606,'Demo Ans 2'!B71) -> 1 | D93: =C93/SUM($C$5:$C$125) -> 0.0016528926
B94: Asst. Cutter Man | C94: =COUNTIF('Row data'!$G$2:$G$606,'Demo Ans 2'!B72) -> 1 | D94: =C94/SUM($C$5:$C$125) -> 0.0016528926
B95: Embroidery Machine Operator | C95: =COUNTIF('Row data'!$G$2:$G$606,'Demo Ans 2'!B74) -> 1 | D95: =C95/SUM($C$5:$C$125) -> 0.0016528926
B96: Sample Man | C96: =COUNTIF('Row data'!$G$2:$G$606,'Demo Ans 2'!B75) -> 1 | D96: =C96/SUM($C$5:$C$125) -> 0.0016528926
B97: Junior Operator | C97: =COUNTIF('Row data'!$G$2:$G$606,'Demo Ans 2'!B76) -> 1 | D97: =C97/SUM($C$5:$C$125) -> 0.0016528926
B98: Junior Sewing Machine Operator | C98: =COUNTIF('Row data'!$G$2:$G$606,'Demo Ans 2'!B77) -> 1 | D98: =C98/SUM($C$5:$C$125) -> 0.0016528926
B99: Lay Women | C99: =COUNTIF('Row data'!$G$2:$G$606,'Demo Ans 2'!B79) -> 1 | D99: =C99/SUM($C$5:$C$125) -> 0.0016528926
B100: Armechar Assistant | C100: =COUNTIF('Row data'!$G$2:$G$606,'Demo Ans 2'!B80) -> 1 | D100: =C100/SUM($C$5:$C$125) -> 0.0016528926
B101: Sweeper | C101: =COUNTIF('Row data'!$G$2:$G$606,'Demo Ans 2'!B81) -> 1 | D101: =C101/SUM($C$5:$C$125) -> 0.0016528926
...

Sheet Demo Ans 3
G1: 11. Identify Employees with Highest Net Pay (Top 3) | N1: 12 Total Overtime Pay by Department | S1: 13 Employees with High Overtime but Low Salary | Z1: 14 Employee Loan vs. Net Pay Analysis
B2: 10. Average Salary by Department (Dynamic Lookup)
G3: EMP Name | H3: Department | I3: Salary | N3: Department | O3: OT | P3: OT Pay | S3: Overtime High and low salary
B4: Department | C4: Average salary (Gross) | G4: =_xlfn.XLOOKUP(I4,Row[Gross],Row[Employee Name],"Not Found",0) -> Rubel | H4: =LOOKUP(G4,Row[DeptName]) -> Production | I4: {=LARGE(Row[Gross],{1;2;3})} -> 185000 | N4: {=_xlfn.UNIQUE(Row[DeptName])} -> Production | O4: =COUNTIFS(Row[DeptName],N4,Row[OT],"Y") -> 386 | P4: =SUMIFS(Row[OT Amount],Row[DeptName],N4) -> 29503 | S4: Employee Name | T4: Low Salery | U4: OT Amount | V4: Net Pay | Z4: Employee Name | AA4: Lone Amount | AB4: Net Payble | AC4: Percent
B5: {=_xlfn.UNIQUE(Row[DeptName])} -> Production | C5: =AVERAGEIF(Row[DeptName],B5,Row[Gross]) -> 16202.812 | G5: =_xlfn.XLOOKUP(I5,Row[Gross],Row[Employee Name],"Not Found",0) -> Bashir | H5: =LOOKUP(G5,Row[DeptName]) -> Admin | I5: 135000 | N5: Utility & Maintenance | O5: =COUNTIFS(Row[DeptName],N5,Row[OT],"Y") -> 1 | P5: =SUMIFS(Row[OT Amount],Row[DeptName],N5) -> 0 | S5: {=_xlfn.SORTBY(_xlfn._xlws.FILTER(_xlfn.HSTACK(Row[Employee Name],Row[Gross],Row[OT Amount],Row[Net Payable]),Row[OT Amount]>0,""),_xlfn._xlws.FILTER(Row[OT Amount],Row[OT Amount]>0),1)} -> Abdul Aziz | T5: 13405 | U5: 4213 | V5: 17968 | Z5: {=_xlfn._xlws.FILTER(Row[Employee Name],Row[Loan]>0)} -> Aminul | AA5: =_xlfn.XLOOKUP(Z5,Row[Employee Name],Row[Loan],,0) -> 15000 | AB5: =_xlfn.XLOOKUP(Z5,Row[Employee Name],Row[Net Payable],,0) -> 17700 | AC5: =AA5/AB5 -> 0.84745763
B6: Utility & Maintenance | C6: =AVERAGEIF(Row[DeptName],B6,Row[Gross]) -> 25814.564 | G6: =_xlfn.XLOOKUP(I6,Row[Gross],Row[Employee Name],"Not Found",0) -> Siam | H6: =LOOKUP(G6,Row[DeptName]) -> Production | I6: 88727 | N6: Admin | O6: =COUNTIFS(Row[DeptName],N6,Row[OT],"Y") -> 11 | P6: =SUMIFS(Row[OT Amount],Row[DeptName],N6) -> 0 | S6: Grace | T6: 15337 | U6: 4626 | V6: 20313 | Z6: Imran | AA6: =_xlfn.XLOOKUP(Z6,Row[Employee Name],Row[Loan],,0) -> 2500 | AB6: =_xlfn.XLOOKUP(Z6,Row[Employee Name],Row[Net Payable],,0) -> 24751 | AC6: =AA6/AB6 -> 0.10100602
B7: Admin | C7: =AVERAGEIF(Row[DeptName],B7,Row[Gross]) -> 21231.843 | N7: Delivery | O7: =COUNTIFS(Row[DeptName],N7,Row[OT],"Y") -> 0 | P7: =SUMIFS(Row[OT Amount],Row[DeptName],N7) -> 0 | S7: George | T7: 13405 | U7: 4634 | V7: 18389 | Z7: Liton | AA7: =_xlfn.XLOOKUP(Z7,Row[Employee Name],Row[Loan],,0) -> 3000 | AB7: =_xlfn.XLOOKUP(Z7,Row[Employee Name],Row[Net Payable],,0) -> 23421 | AC7: =AA7/AB7 -> 0.12809018
B8: Delivery | C8: =AVERAGEIF(Row[DeptName],B8,Row[Gross]) -> 33999.5 | N8: HR & Compliance | O8: =COUNTIFS(Row[DeptName],N8,Row[OT],"Y") -> 0 | P8: =SUMIFS(Row[OT Amount],Row[DeptName],N8) -> 0 | S8: Grayson | T8: 13405 | U8: 4634 | V8: 18389 | Z8: Rashid | AA8: =_xlfn.XLOOKUP(Z8,Row[Employee Name],Row[Loan],,0) -> 5000 | AB8: =_xlfn.XLOOKUP(Z8,Row[Employee Name],Row[Net Payable],,0) -> 30533 | AC8: =AA8/AB8 -> 0.16375725
B9: HR & Compliance | C9: =AVERAGEIF(Row[DeptName],B9,Row[Gross]) -> 32836.5 | N9: IT | O9: =COUNTIFS(Row[DeptName],N9,Row[OT],"Y") -> 0 | P9: =SUMIFS(Row[OT Amount],Row[DeptName],N9) -> 0 | S9: Gabriel | T9: 14549 | U9: 4653 | V9: 19552 | Z9: Sagor | AA9: =_xlfn.XLOOKUP(Z9,Row[Employee Name],Row[Loan],,0) -> 500 | AB9: =_xlfn.XLOOKUP(Z9,Row[Employee Name],Row[Net Payable],,0) -> 23441 | AC9: =AA9/AB9 -> 0.021330148
B10: IT | C10: =AVERAGEIF(Row[DeptName],B10,Row[Gross]) -> 41420 | N10: Store | O10: =COUNTIFS(Row[DeptName],N10,Row[OT],"Y") -> 0 | P10: =SUMIFS(Row[OT Amount],Row[DeptName],N10) -> 0 | S10: Prosenjit Bappi | T10: 18388 | U10: 6743 | V10: 24481 | Z10: Shafayet | AA10: =_xlfn.XLOOKUP(Z10,Row[Employee Name],Row[Loan],,0) -> 4000 | AB10: =_xlfn.XLOOKUP(Z10,Row[Employee Name],Row[Net Payable],,0) -> 37515 | AC10: =AA10/AB10 -> 0.10662402
B11: Store | C11: =AVERAGEIF(Row[DeptName],B11,Row[Gross]) -> 20718.417 | N11: Accounts | O11: =COUNTIFS(Row[DeptName],N11,Row[OT],"Y") -> 0 | P11: =SUMIFS(Row[OT Amount],Row[DeptName],N11) -> 0 | Z11: Siam | AA11: =_xlfn.XLOOKUP(Z11,Row[Employee Name],Row[Loan],,0) -> 5000 | AB11: =_xlfn.XLOOKUP(Z11,Row[Employee Name],Row[Net Payable],,0) -> 81927 | AC11: =AA11/AB11 -> 0.061029941
B12: Accounts | C12: =AVERAGEIF(Row[DeptName],B12,Row[Gross]) -> 47905.5 | Z12: Sujan | AA12: =_xlfn.XLOOKUP(Z12,Row[Employee Name],Row[Loan],,0) -> 1500 | AB12: =_xlfn.XLOOKUP(Z12,Row[Employee Name],Row[Net Payable],,0) -> 14868 | AC12: =AA12/AB12 -> 0.10088781
Z13: Wahid | AA13: =_xlfn.XLOOKUP(Z13,Row[Employee Name],Row[Loan],,0) -> 3000 | AB13: =_xlfn.XLOOKUP(Z13,Row[Employee Name],Row[Net Payable],,0) -> 17136 | AC13: =AA13/AB13 -> 0.17507003
Z14: Alia | AA14: =_xlfn.XLOOKUP(Z14,Row[Employee Name],Row[Loan],,0) -> 3000 | AB14: =_xlfn.XLOOKUP(Z14,Row[Employee Name],Row[Net Payable],,0) -> 34942 | AC14: =AA14/AB14 -> 0.085856562
Z15: Anika | AA15: =_xlfn.XLOOKUP(Z15,Row[Employee Name],Row[Loan],,0) -> 2000 | AB15: =_xlfn.XLOOKUP(Z15,Row[Employee Name],Row[Net Payable],,0) -> 27457 | AC15: =AA15/AB15 -> 0.07284117
Z16: Labiba | AA16: =_xlfn.XLOOKUP(Z16,Row[Employee Name],Row[Loan],,0) -> 500 | AB16: =_xlfn.XLOOKUP(Z16,Row[Employee Name],Row[Net Payable],,0) -> 15063 | AC16: =AA16/AB16 -> 0.033193919
Z17: Maleka | AA17: =_xlfn.XLOOKUP(Z17,Row[Employee Name],Row[Loan],,0) -> 5000 | AB17: =_xlfn.XLOOKUP(Z17,Row[Employee Name],Row[Net Payable],,0) -> 20461 | AC17: =AA17/AB17 -> 0.24436733
Z18: Maria | AA18: =_xlfn.XLOOKUP(Z18,Row[Employee Name],Row[Loan],,0) -> 1000 | AB18: =_xlfn.XLOOKUP(Z18,Row[Employee Name],Row[Net Payable],,0) -> 26145 | AC18: =AA18/AB18 -> 0.038248231
Z19: Moushumi | AA19: =_xlfn.XLOOKUP(Z19,Row[Employee Name],Row[Loan],,0) -> 1000 | AB19: =_xlfn.XLOOKUP(Z19,Row[Employee Name],Row[Net Payable],,0) -> 14805 | AC19: =AA19/AB19 -> 0.067544748
Z20: Nasima | AA20: =_xlfn.XLOOKUP(Z20,Row[Employee Name],Row[Loan],,0) -> 5000 | AB20: =_xlfn.XLOOKUP(Z20,Row[Employee Name],Row[Net Payable],,0) -> 31078 | AC20: =AA20/AB20 -> 0.16088551
Z21: Nazia | AA21: =_xlfn.XLOOKUP(Z21,Row[Employee Name],Row[Loan],,0) -> 2000 | AB21: =_xlfn.XLOOKUP(Z21,Row[Employee Name],Row[Net Payable],,0) -> 19495 | AC21: =AA21/AB21 -> 0.10259041
Z22: Ritu | AA22: =_xlfn.XLOOKUP(Z22,Row[Employee Name],Row[Loan],,0) -> 500 | AB22: =_xlfn.XLOOKUP(Z22,Row[Employee Name],Row[Net Payable],,0) -> 15063 | AC22: =AA22/AB22 -> 0.033193919
Z23: Rumana | AA23: =_xlfn.XLOOKUP(Z23,Row[Employee Name],Row[Loan],,0) -> 3000 | AB23: =_xlfn.XLOOKUP(Z23,Row[Employee Name],Row[Net Payable],,0) -> 23705 | AC23: =AA23/AB23 -> 0.12655558
Z24: Tasfia | AA24: =_xlfn.XLOOKUP(Z24,Row[Employee Name],Row[Loan],,0) -> 1500 | AB24: =_xlfn.XLOOKUP(Z24,Row[Employee Name],Row[Net Payable],,0) -> 13837 | AC24: =AA24/AB24 -> 0.108405
... Z32: Kaitlyn | AA32: =_xlfn.XLOOKUP(Z32,Row[Employee Name],Row[Loan],,0) -> 500 | AB32: =_xlfn.XLOOKUP(Z32,Row[Employee Name],Row[Net Payable],,0) -> 13155 | AC32: =AA32/AB32 -> 0.038008362

Sheet Sheet2
B2: 1. How many employees are currently working in the company?
B4: 404 | D4: COUNT
B6: 2. What is the gender distribution of employees?
B8: 400 Male and 205 Female | D8: Countif
B11: 3. What is the average age of employees Male and Femaile? | D11: Averageif
B15: 4. How many employees joined each year?
B17: 6 | D17: Countifs
B19: 5. What is the attrition rate (employees who quit per year)?
B21: Year | C21: Total Emmployee | D21: Total Quit | E21: Percentage
B22: {=_xlfn.TAKE(_xlfn._xlws.SORT(_xlfn.UNIQUE(TEXT('Row data'!$I$2:$I$606,"YYYY")),1,-1),COUNTIF(_xlfn.ANCHORARRAY(D22),">0"))} -> 2025 | C22: {=COUNTIFS('Row data'!$K$2:$K$606,_xlfn.ANCHORARRAY(B22))} -> 4 | D22: {=COUNTIF('Row data'!$K$2:$K$606,_xlfn.ANCHORARRAY(B22))} -> 4 | E22: {=ROUND(_xlfn.ANCHORARRAY(D22)/SUM(_xlfn.ANCHORARRAY(D22)),2)} -> 0.02 | G22: Row Labels | H22: Count of Employee Name | I22: Count of QuitDate
B23: 2024 | C23: 10 | D23: 10 | E23: 0.05 | G23: 2025 | H23: 6 | I23: 4
B24: 2023 | C24: 10 | D24: 10 | E24: 0.05 | G24: 2024 | H24: 14 | I24: 12
B25: 2022 | C25: 135 | D25: 135 | E25: 0.67 | G25: 2023 | H25: 82 | I25: 43
B26: 2021 | C26: 9 | D26: 9 | E26: 0.04 | G26: 2022 | H26: 74 | I26: 9
B27: 2020 | C27: 7 | D27: 7 | E27: 0.03 | G27: 2021 | H27: 80 | I27: 17
B28: 2019 | C28: 14 | D28: 14 | E28: 0.07 | G28: 2020 | H28: 26 | I28: 6
B29: 2018 | C29: 12 | D29: 12 | E29: 0.06 | G29: 2019 | H29: 16 | I29: 2
G30: 2018 | H30: 45 | I30: 15
G31: 2017 | H31: 61 | I31: 21
G32: 2016 | H32: 28 | I32: 8
G33: 2015 | H33: 29 | I33: 10
G34: 2014 | H34: 20 | I34: 10
G35: 2013 | H35: 15 | I35: 5
G36: 2012 | H36: 15 | I36: 6
G37: 2011 | H37: 16 | I37: 2
G38: 2010 | H38: 17 | I38: 6
G39: 2009 | H39: 8 | I39: 5
G40: 2008 | H40: 8 | I40: 3
G41: 2007 | H41: 9 | I41: 1
... G43: 2005 | H43: 1 | I43: 1
G44: 2004 | H44: 1
G45: 2003 | H45: 10 | I45: 2
G46: 2002 | H46: 4 | I46: 2
G47: 2001 | H47: 6 | I47: 6
G48: 2000 | H48: 2
G49: 1999 | H49: 3 | I49: 2
G50: 1998 | H50: 3 | I50: 1
G51: 1997 | H51: 1
G52: 1996 | H52: 2 | I52: 1
G53: 1995 | H53: 2
G54: Grand Total | H54: 605 | I54: 201
